{
  "Version": 3,
  "Meta": {
    "Duration": 3.4,
    "Fps": 30.0,
    "Loop": true,
    "AreBeziersRestricted": true,
    "FadeInTime": 2.0,
    "FadeOutTime": 0.2,
    "CurveCount": 127,
    "TotalSegmentCount": 470,
    "TotalPointCount": 887,
    "UserDataCount": 0,
    "TotalUserDataSize": 0
  },
  "Curves": [
    {
      "Target": "Parameter",
      "Id": "ParamCheek",
      "FadeInTime": -1.0,
      "FadeOutTime": -1.0,
      "Segments": [
        0,
        0,
        0,
        1.3,
        0.6,
        0,
        3.4,
        0
      ]
    },
    {
      "Target": "Parameter",
      "Id": "ParamEyeROpen",
      "FadeInTime": -1.0,
      "FadeOutTime": -1.0,
      "Segments": [
        0,
        0.5,
        0,
        1.3,
        0.5,
        0,
        3.4,
        0.5
      ]
    },
    {
      "Target": "Parameter",
      "Id": "ParamEyeRSmile",
      "FadeInTime": -1.0,
      "FadeOutTime": -1.0,
      "Segments": [
        0,
        0,
        0,
        1.3,
        1,
        0,
        3.4,
        0
      ]
    },
    {
      "Target": "Parameter",
      "Id": "Param18",
      "FadeInTime": -1.0,
      "FadeOutTime": -1.0,
      "Segments": [
        0,
        -1,
        0,
        1.3,
        -1,
        0,
        3.4,
        -1
      ]
    },
    {
      "Target": "Parameter",
      "Id": "ParamEyeLOpen",
      "FadeInTime": -1.0,
      "FadeOutTime": -1.0,
      "Segments": [
        0,
        0.5,
        0,
        0.717,
        0.5,
        0,
        1.133,
        0,
        0,
        1.3,
        0,
        0,
        1.633,
        0,
        0,
        2.017,
        0.5,
        0,
        3.4,
        0.5
      ]
    },
    {
      "Target": "Parameter",
      "Id": "ParamEyeLSmile",
      "FadeInTime": -1.0,
      "FadeOutTime": -1.0,
      "Segments": [
        0,
        0,
        0,
        1.3,
        1,
        0,
        3.4,
        0
      ]
    },
    {
      "Target": "Parameter",
      "Id": "Param19",
      "FadeInTime": -1.0,
      "FadeOutTime": -1.0,
      "Segments": [
        0,
        -1,
        0,
        3.4,
        -1
      ]
    },
    {
      "Target": "Parameter",
      "Id": "ParamEyeBallX",
      "FadeInTime": -1.0,
      "FadeOutTime": -1.0,
      "Segments": [
        0,
        0,
        0,
        3.4,
        0
      ]
    },
    {
      "Target": "Parameter",
      "Id": "ParamEyeBallY",
      "FadeInTime": -1.0,
      "FadeOutTime": -1.0,
      "Segments": [
        0,
        0,
        0,
        3.4,
        0
      ]
    },
    {
      "Target": "Parameter",
      "Id": "ParamBrowLAngle",
      "FadeInTime": -1.0,
      "FadeOutTime": -1.0,
      "Segments": [
        0,
        0,
        0,
        3.4,
        0
      ]
    },
    {
      "Target": "Parameter",
      "Id": "ParamBrowRAngle",
      "FadeInTime": -1.0,
      "FadeOutTime": -1.0,
      "Segments": [
        0,
        0,
        0,
        3.4,
        0
      ]
    },
    {
      "Target": "Parameter",
      "Id": "ParamBrowLForm",
      "FadeInTime": -1.0,
      "FadeOutTime": -1.0,
      "Segments": [
        0,
        0,
        0,
        1.3,
        1,
        0,
        3.4,
        0
      ]
    },
    {
      "Target": "Parameter",
      "Id": "ParamBrowRForm",
      "FadeInTime": -1.0,
      "FadeOutTime": -1.0,
      "Segments": [
        0,
        0,
        0,
        1.3,
        1,
        0,
        3.4,
        0
      ]
    },
    {
      "Target": "Parameter",
      "Id": "ParamMouthForm",
      "FadeInTime": -1.0,
      "FadeOutTime": -1.0,
      "Segments": [
        0,
        0,
        0,
        1.3,
        1,
        0,
        3.4,
        0
      ]
    },
    {
      "Target": "Parameter",
      "Id": "ParamMouthOpenY",
      "FadeInTime": -1.0,
      "FadeOutTime": -1.0,
      "Segments": [
        0,
        1,
        0,
        1.3,
        1,
        0,
        3.4,
        1
      ]
    },
    {
      "Target": "Parameter",
      "Id": "Param16",
      "FadeInTime": -1.0,
      "FadeOutTime": -1.0,
      "Segments": [
        0,
        0,
        0,
        1.067,
        -0.7,
        0,
        2.317,
        -0.1,
        0,
        2.867,
        -0.6,
        0,
        3.4,
        0
      ]
    },
    {
      "Target": "Parameter",
      "Id": "Param17",
      "FadeInTime": -1.0,
      "FadeOutTime": -1.0,
      "Segments": [
        0,
        0,
        1,
        0.356,
        0.24,
        0.711,
        0.6,
        1.067,
        0.6,
        0,
        2.317,
        -1,
        1,
        2.5,
        -1,
        2.684,
        -0.323,
        2.867,
        -0.2,
        1,
        3.045,
        -0.08,
        3.222,
        -0.12,
        3.4,
        0
      ]
    },
    {
      "Target": "Parameter",
      "Id": "Param47",
      "FadeInTime": -1.0,
      "FadeOutTime": -1.0,
      "Segments": [
        0,
        0,
        0,
        3.4,
        0
      ]
    },
    {
      "Target": "Parameter",
      "Id": "Param33",
      "FadeInTime": -1.0,
      "FadeOutTime": -1.0,
      "Segments": [
        0,
        0,
        1,
        0.2,
        0.333,
        0.4,
        0.5,
        0.6,
        0.5,
        1,
        0.833,
        0.5,
        1.067,
        0.206,
        1.3,
        0,
        1,
        1.639,
        -0.3,
        1.978,
        -0.356,
        2.317,
        -0.356,
        1,
        2.678,
        -0.356,
        3.039,
        -0.303,
        3.4,
        0
      ]
    },
    {
      "Target": "Parameter",
      "Id": "Param35",
      "FadeInTime": -1.0,
      "FadeOutTime": -1.0,
      "Segments": [
        0,
        0,
        1,
        0.2,
        -0.325,
        0.4,
        -0.4,
        0.6,
        -0.4,
        1,
        0.833,
        -0.4,
        1.067,
        -0.222,
        1.3,
        0,
        1,
        1.639,
        0.323,
        1.978,
        0.434,
        2.317,
        0.434,
        1,
        2.678,
        0.434,
        3.039,
        0.337,
        3.4,
        0
      ]
    },
    {
      "Target": "Parameter",
      "Id": "ParamBreath",
      "FadeInTime": -1.0,
      "FadeOutTime": -1.0,
      "Segments": [
        0,
        0.5,
        0,
        0.817,
        0.7,
        0,
        1.783,
        0,
        0,
        2.517,
        0.7,
        0,
        3.4,
        0.5
      ]
    },
    {
      "Target": "Parameter",
      "Id": "Param43",
      "FadeInTime": -1.0,
      "FadeOutTime": -1.0,
      "Segments": [
        0,
        -30,
        0,
        0.817,
        30,
        0,
        1.783,
        -30,
        0,
        2.517,
        -11,
        0,
        3.4,
        -30
      ]
    },
    {
      "Target": "Parameter",
      "Id": "ParamBodyAngleX",
      "FadeInTime": -1.0,
      "FadeOutTime": -1.0,
      "Segments": [
        0,
        0,
        1,
        0.233,
        0,
        0.467,
        -2.415,
        0.7,
        -5.475,
        1,
        0.811,
        -6.932,
        0.922,
        -8.205,
        1.033,
        -8.745,
        1,
        1.25,
        -9.798,
        1.466,
        -10,
        1.683,
        -10,
        1,
        1.883,
        -10,
        2.083,
        -10,
        2.283,
        -8.577,
        1,
        2.655,
        -5.376,
        3.028,
        0,
        3.4,
        0
      ]
    },
    {
      "Target": "Parameter",
      "Id": "Param26",
      "FadeInTime": -1.0,
      "FadeOutTime": -1.0,
      "Segments": [
        0,
        -0.478,
        1,
        0.206,
        -0.572,
        0.411,
        -0.6,
        0.617,
        -0.6,
        1,
        0.845,
        -0.6,
        1.072,
        -0.318,
        1.3,
        -0.176,
        1,
        1.539,
        -0.027,
        1.778,
        -0.024,
        2.017,
        -0.024,
        1,
        2.139,
        -0.024,
        2.261,
        -0.079,
        2.383,
        -0.3,
        1,
        2.528,
        -0.562,
        2.672,
        -0.774,
        2.817,
        -0.774,
        1,
        3.011,
        -0.774,
        3.206,
        -0.773,
        3.4,
        -0.753
      ]
    },
    {
      "Target": "Parameter",
      "Id": "Param5",
      "FadeInTime": -1.0,
      "FadeOutTime": -1.0,
      "Segments": [
        0,
        0,
        0,
        0.433,
        -13,
        1,
        0.566,
        -13,
        0.7,
        6.854,
        0.833,
        17,
        1,
        0.989,
        28.837,
        1.144,
        30,
        1.3,
        30,
        0,
        1.95,
        -12,
        0,
        2.5,
        30,
        0,
        3.083,
        -10.27,
        0,
        3.4,
        0
      ]
    },
    {
      "Target": "Parameter",
      "Id": "Param6",
      "FadeInTime": -1.0,
      "FadeOutTime": -1.0,
      "Segments": [
        0,
        0,
        1,
        0.144,
        0,
        0.289,
        1.718,
        0.433,
        11,
        1,
        0.505,
        15.641,
        0.578,
        29.404,
        0.65,
        29.404,
        0,
        1.317,
        -13,
        0,
        1.95,
        29.404,
        0,
        2.517,
        -11.671,
        0,
        3.033,
        25.935,
        0,
        3.4,
        0
      ]
    },
    {
      "Target": "Parameter",
      "Id": "Param37",
      "FadeInTime": -1.0,
      "FadeOutTime": -1.0,
      "Segments": [
        0,
        0,
        0,
        3.4,
        0
      ]
    },
    {
      "Target": "Parameter",
      "Id": "Param2",
      "FadeInTime": -1.0,
      "FadeOutTime": -1.0,
      "Segments": [
        0,
        0,
        0,
        3.4,
        0
      ]
    },
    {
      "Target": "Parameter",
      "Id": "Param20",
      "FadeInTime": -1.0,
      "FadeOutTime": -1.0,
      "Segments": [
        0,
        0,
        0,
        3.4,
        0
      ]
    },
    {
      "Target": "Parameter",
      "Id": "Param4",
      "FadeInTime": -1.0,
      "FadeOutTime": -1.0,
      "Segments": [
        0,
        0,
        0,
        0.433,
        -1,
        0,
        0.933,
        0,
        0,
        3.4,
        0
      ]
    },
    {
      "Target": "Parameter",
      "Id": "Param7",
      "FadeInTime": -1.0,
      "FadeOutTime": -1.0,
      "Segments": [
        0,
        0,
        0,
        0.433,
        0,
        1,
        0.566,
        0,
        0.7,
        -0.227,
        0.833,
        -0.606,
        1,
        0.933,
        -0.89,
        1.033,
        -1,
        1.133,
        -1,
        0,
        1.633,
        -1,
        0,
        3.4,
        0
      ]
    },
    {
      "Target": "Parameter",
      "Id": "Param8",
      "FadeInTime": -1.0,
      "FadeOutTime": -1.0,
      "Segments": [
        0,
        0,
        0,
        0.883,
        0,
        0,
        1.3,
        -1,
        0,
        1.883,
        -1,
        0,
        2.033,
        -1,
        0,
        2.333,
        0,
        0,
        2.533,
        0,
        0,
        3.4,
        0
      ]
    },
    {
      "Target": "Parameter",
      "Id": "Param9",
      "FadeInTime": -1.0,
      "FadeOutTime": -1.0,
      "Segments": [
        0,
        0,
        0,
        1.3,
        -1,
        0,
        1.633,
        -1,
        0,
        3.4,
        0
      ]
    },
    {
      "Target": "Parameter",
      "Id": "Param10",
      "FadeInTime": -1.0,
      "FadeOutTime": -1.0,
      "Segments": [
        0,
        0,
        0,
        0.717,
        0,
        1,
        0.789,
        0,
        0.861,
        -10.688,
        0.933,
        -17,
        1,
        1.055,
        -27.682,
        1.178,
        -30,
        1.3,
        -30,
        0,
        1.883,
        -30,
        0,
        2.033,
        -30,
        1,
        2.133,
        -30,
        2.233,
        -15.256,
        2.333,
        -6,
        1,
        2.4,
        0.171,
        2.466,
        0,
        2.533,
        0,
        0,
        3.4,
        0
      ]
    },
    {
      "Target": "Parameter",
      "Id": "Param23",
      "FadeInTime": -1.0,
      "FadeOutTime": -1.0,
      "Segments": [
        0,
        0,
        0,
        0.733,
        -1,
        1,
        0.922,
        -1,
        1.111,
        -0.117,
        1.3,
        0,
        1,
        1.494,
        0.12,
        1.689,
        0.1,
        1.883,
        0.1,
        1,
        1.933,
        0.1,
        1.983,
        0.143,
        2.033,
        0,
        1,
        2.133,
        -0.286,
        2.233,
        -1,
        2.333,
        -1,
        0,
        2.533,
        -1,
        0,
        3.4,
        0
      ]
    },
    {
      "Target": "Parameter",
      "Id": "Param24",
      "FadeInTime": -1.0,
      "FadeOutTime": -1.0,
      "Segments": [
        0,
        0,
        0,
        0.483,
        0.5,
        0,
        0.833,
        -0.1,
        0,
        1.083,
        -0.1,
        0,
        1.3,
        0,
        0,
        3.4,
        0
      ]
    },
    {
      "Target": "Parameter",
      "Id": "Param",
      "FadeInTime": -1.0,
      "FadeOutTime": -1.0,
      "Segments": [
        0,
        -30,
        1,
        0.25,
        -30,
        0.5,
        -20.918,
        0.75,
        -1,
        1,
        1,
        18.918,
        1.25,
        29.819,
        1.5,
        29.819,
        1,
        1.861,
        29.819,
        2.222,
        21.429,
        2.583,
        -1,
        1,
        2.855,
        -17.908,
        3.128,
        -30,
        3.4,
        -30
      ]
    },
    {
      "Target": "Parameter",
      "Id": "Param11",
      "FadeInTime": -1.0,
      "FadeOutTime": -1.0,
      "Segments": [
        0,
        0,
        0,
        3.4,
        0
      ]
    },
    {
      "Target": "Parameter",
      "Id": "Param21",
      "FadeInTime": -1.0,
      "FadeOutTime": -1.0,
      "Segments": [
        0,
        0,
        0,
        0.5,
        0.1,
        1,
        0.594,
        0.1,
        0.689,
        0.047,
        0.783,
        0,
        1,
        0.872,
        -0.044,
        0.961,
        -0.047,
        1.05,
        -0.1,
        1,
        1.133,
        -0.15,
        1.217,
        -0.351,
        1.3,
        -0.5,
        1,
        1.439,
        -0.748,
        1.578,
        -0.9,
        1.717,
        -0.9,
        1,
        1.817,
        -0.9,
        1.917,
        -0.818,
        2.017,
        -0.6,
        1,
        2.067,
        -0.491,
        2.117,
        -0.269,
        2.167,
        -0.2,
        1,
        2.206,
        -0.146,
        2.244,
        -0.123,
        2.283,
        -0.1,
        1,
        2.405,
        -0.027,
        2.528,
        0,
        2.65,
        0,
        0,
        3.4,
        0
      ]
    },
    {
      "Target": "Parameter",
      "Id": "Param22",
      "FadeInTime": -1.0,
      "FadeOutTime": -1.0,
      "Segments": [
        0,
        0,
        0,
        3.4,
        0
      ]
    },
    {
      "Target": "Parameter",
      "Id": "Param38",
      "FadeInTime": -1.0,
      "FadeOutTime": -1.0,
      "Segments": [
        0,
        0,
        0,
        3.4,
        0
      ]
    },
    {
      "Target": "Parameter",
      "Id": "Param39",
      "FadeInTime": -1.0,
      "FadeOutTime": -1.0,
      "Segments": [
        0,
        0,
        0,
        3.4,
        0
      ]
    },
    {
      "Target": "Parameter",
      "Id": "Param40",
      "FadeInTime": -1.0,
      "FadeOutTime": -1.0,
      "Segments": [
        0,
        0,
        0,
        3.4,
        0
      ]
    },
    {
      "Target": "Parameter",
      "Id": "Param3",
      "FadeInTime": -1.0,
      "FadeOutTime": -1.0,
      "Segments": [
        0,
        0,
        0,
        0.65,
        25,
        0,
        1.3,
        -30,
        0,
        2.017,
        16,
        0,
        2.783,
        -21,
        1,
        2.989,
        -21,
        3.194,
        -14.866,
        3.4,
        0
      ]
    },
    {
      "Target": "Parameter",
      "Id": "Param13",
      "FadeInTime": -1.0,
      "FadeOutTime": -1.0,
      "Segments": [
        0,
        0,
        0,
        0.65,
        -0.9,
        1,
        0.867,
        -0.9,
        1.083,
        -0.849,
        1.3,
        -0.4,
        1,
        1.544,
        0.107,
        1.789,
        0.7,
        2.033,
        0.7,
        0,
        2.533,
        -0.7,
        0,
        3.4,
        0
      ]
    },
    {
      "Target": "Parameter",
      "Id": "Param14",
      "FadeInTime": -1.0,
      "FadeOutTime": -1.0,
      "Segments": [
        0,
        0,
        0,
        0.65,
        0.8,
        1,
        0.867,
        0.8,
        1.083,
        0.57,
        1.3,
        0.1,
        1,
        1.544,
        -0.43,
        1.789,
        -0.7,
        2.033,
        -0.7,
        0,
        2.533,
        0.7,
        0,
        3.4,
        0
      ]
    },
    {
      "Target": "Parameter",
      "Id": "Param15",
      "FadeInTime": -1.0,
      "FadeOutTime": -1.0,
      "Segments": [
        0,
        0,
        0,
        0.65,
        -0.9,
        1,
        0.867,
        -0.9,
        1.083,
        -0.783,
        1.3,
        -0.3,
        1,
        1.544,
        0.245,
        1.789,
        0.7,
        2.033,
        0.7,
        0,
        2.533,
        -0.7,
        0,
        3.4,
        0
      ]
    },
    {
      "Target": "Parameter",
      "Id": "Param48",
      "FadeInTime": -1.0,
      "FadeOutTime": -1.0,
      "Segments": [
        0,
        0,
        0,
        1.3,
        -0.8,
        0,
        2.4,
        0.5,
        0,
        3.4,
        0
      ]
    },
    {
      "Target": "Parameter",
      "Id": "Param_Angle_Rotation61",
      "FadeInTime": -1.0,
      "FadeOutTime": -1.0,
      "Segments": [
        0,
        0,
        0,
        1.3,
        -10,
        0,
        3.4,
        0
      ]
    },
    {
      "Target": "Parameter",
      "Id": "Param_Angle_Rotation62",
      "FadeInTime": -1.0,
      "FadeOutTime": -1.0,
      "Segments": [
        0,
        0,
        0,
        1.3,
        10,
        0,
        3.4,
        0
      ]
    },
    {
      "Target": "Parameter",
      "Id": "Param_Angle_Rotation75",
      "FadeInTime": -1.0,
      "FadeOutTime": -1.0,
      "Segments": [
        0,
        0,
        0,
        0.95,
        -7,
        0,
        1.917,
        5,
        0,
        2.717,
        -7,
        0,
        3.4,
        0
      ]
    },
    {
      "Target": "Parameter",
      "Id": "Param_Angle_Rotation76",
      "FadeInTime": -1.0,
      "FadeOutTime": -1.0,
      "Segments": [
        0,
        0,
        0,
        0.95,
        -10,
        0,
        1.917,
        5,
        0,
        2.717,
        -9,
        0,
        3.4,
        0
      ]
    },
    {
      "Target": "Parameter",
      "Id": "Param_Angle_Rotation66",
      "FadeInTime": -1.0,
      "FadeOutTime": -1.0,
      "Segments": [
        0,
        0,
        0,
        0.95,
        -10,
        0,
        1.917,
        7,
        0,
        2.717,
        -7,
        0,
        3.4,
        0
      ]
    },
    {
      "Target": "Parameter",
      "Id": "Param_Angle_Rotation67",
      "FadeInTime": -1.0,
      "FadeOutTime": -1.0,
      "Segments": [
        0,
        0,
        1,
        0.317,
        -3.63,
        0.633,
        -10,
        0.95,
        -10,
        0,
        1.917,
        4,
        0,
        2.717,
        -8,
        1,
        2.945,
        -8,
        3.172,
        -3.97,
        3.4,
        0
      ]
    },
    {
      "Target": "Parameter",
      "Id": "Param_Angle_Rotation57",
      "FadeInTime": -1.0,
      "FadeOutTime": -1.0,
      "Segments": [
        0,
        0,
        1,
        0.317,
        -4.6,
        0.633,
        -8,
        0.95,
        -8,
        0,
        1.917,
        3,
        0,
        2.717,
        -3,
        0,
        3.4,
        0
      ]
    },
    {
      "Target": "Parameter",
      "Id": "Param_Angle_Rotation58",
      "FadeInTime": -1.0,
      "FadeOutTime": -1.0,
      "Segments": [
        0,
        0,
        1,
        0.317,
        -5.093,
        0.633,
        -7,
        0.95,
        -7,
        0,
        1.917,
        7,
        0,
        2.717,
        -10,
        0,
        3.4,
        0
      ]
    },
    {
      "Target": "Parameter",
      "Id": "Param_Angle_Rotation63",
      "FadeInTime": -1.0,
      "FadeOutTime": -1.0,
      "Segments": [
        0,
        0,
        1,
        0.433,
        -0.885,
        0.867,
        -1,
        1.3,
        -1,
        1,
        1.672,
        -1,
        2.045,
        -0.609,
        2.417,
        1,
        1,
        2.572,
        1.672,
        2.728,
        3,
        2.883,
        3,
        1,
        3.055,
        3,
        3.228,
        0.352,
        3.4,
        0
      ]
    },
    {
      "Target": "Parameter",
      "Id": "Param_Angle_Rotation64",
      "FadeInTime": -1.0,
      "FadeOutTime": -1.0,
      "Segments": [
        0,
        0,
        0,
        1.3,
        -10,
        0,
        2.883,
        -10,
        0,
        3.4,
        0
      ]
    },
    {
      "Target": "Parameter",
      "Id": "Param_Angle_Rotation79",
      "FadeInTime": -1.0,
      "FadeOutTime": -1.0,
      "Segments": [
        0,
        0,
        0,
        0.7,
        -2,
        0,
        1.483,
        -2,
        0,
        3.4,
        0
      ]
    },
    {
      "Target": "Parameter",
      "Id": "Param_Angle_Rotation80",
      "FadeInTime": -1.0,
      "FadeOutTime": -1.0,
      "Segments": [
        0,
        0,
        1,
        0.233,
        -3.012,
        0.467,
        -3,
        0.7,
        -3,
        0,
        1.483,
        10,
        0,
        2.917,
        -3,
        0,
        3.4,
        0
      ]
    },
    {
      "Target": "Parameter",
      "Id": "Param_Angle_Rotation81",
      "FadeInTime": -1.0,
      "FadeOutTime": -1.0,
      "Segments": [
        0,
        0,
        1,
        0.233,
        -0.286,
        0.467,
        -3,
        0.7,
        -3,
        0,
        1.483,
        1,
        0,
        3.4,
        0
      ]
    },
    {
      "Target": "Parameter",
      "Id": "Param_Angle_Rotation82",
      "FadeInTime": -1.0,
      "FadeOutTime": -1.0,
      "Segments": [
        0,
        0,
        1,
        0.233,
        -2.959,
        0.467,
        -3,
        0.7,
        -3,
        0,
        1.483,
        9,
        0,
        2.917,
        -3,
        0,
        3.4,
        0
      ]
    },
    {
      "Target": "Parameter",
      "Id": "Param_Angle_Rotation83",
      "FadeInTime": -1.0,
      "FadeOutTime": -1.0,
      "Segments": [
        0,
        0,
        0,
        0.7,
        -8,
        1,
        0.961,
        -8,
        1.222,
        -5.315,
        1.483,
        -4,
        1,
        2.122,
        -0.782,
        2.761,
        0,
        3.4,
        0
      ]
    },
    {
      "Target": "Parameter",
      "Id": "Param_Angle_Rotation84",
      "FadeInTime": -1.0,
      "FadeOutTime": -1.0,
      "Segments": [
        0,
        0,
        1,
        0.233,
        -5.153,
        0.467,
        -6,
        0.7,
        -6,
        0,
        1.483,
        10,
        0,
        2.917,
        -4,
        0,
        3.4,
        0
      ]
    },
    {
      "Target": "Parameter",
      "Id": "Param_Angle_Rotation85",
      "FadeInTime": -1.0,
      "FadeOutTime": -1.0,
      "Segments": [
        0,
        0.04,
        0,
        1.483,
        -5,
        0,
        3.4,
        0.04
      ]
    },
    {
      "Target": "Parameter",
      "Id": "Param_Angle_Rotation86",
      "FadeInTime": -1.0,
      "FadeOutTime": -1.0,
      "Segments": [
        0,
        0,
        1,
        0.233,
        -3.799,
        0.467,
        -4,
        0.7,
        -4,
        0,
        1.483,
        10,
        0,
        2.917,
        -4,
        0,
        3.4,
        0
      ]
    },
    {
      "Target": "Parameter",
      "Id": "Param_Angle_Rotation87",
      "FadeInTime": -1.0,
      "FadeOutTime": -1.0,
      "Segments": [
        0,
        0.04,
        1,
        0.233,
        0.04,
        0.467,
        -6.125,
        0.7,
        -8,
        1,
        0.961,
        -10,
        1.222,
        -10,
        1.483,
        -10,
        0,
        3.4,
        0.04
      ]
    },
    {
      "Target": "Parameter",
      "Id": "Param_Angle_Rotation88",
      "FadeInTime": -1.0,
      "FadeOutTime": -1.0,
      "Segments": [
        0,
        0,
        1,
        0.233,
        -3.012,
        0.467,
        -3,
        0.7,
        -3,
        0,
        1.483,
        10,
        0,
        2.917,
        -4,
        0,
        3.4,
        0
      ]
    },
    {
      "Target": "Parameter",
      "Id": "Param_Angle_Rotation89",
      "FadeInTime": -1.0,
      "FadeOutTime": -1.0,
      "Segments": [
        0,
        0.02,
        1,
        0.233,
        -1.008,
        0.467,
        -3,
        0.7,
        -3,
        0,
        1.483,
        4,
        0,
        2.917,
        -1,
        1,
        3.078,
        -1,
        3.239,
        -0.859,
        3.4,
        0.02
      ]
    },
    {
      "Target": "Parameter",
      "Id": "Param_Angle_Rotation90",
      "FadeInTime": -1.0,
      "FadeOutTime": -1.0,
      "Segments": [
        0,
        0,
        1,
        0.233,
        -4.509,
        0.467,
        -5,
        0.7,
        -5,
        0,
        1.483,
        10,
        0,
        2.917,
        -3,
        1,
        3.078,
        -3,
        3.239,
        -1.541,
        3.4,
        0
      ]
    },
    {
      "Target": "Parameter",
      "Id": "Param_Angle_Rotation91",
      "FadeInTime": -1.0,
      "FadeOutTime": -1.0,
      "Segments": [
        0,
        0,
        1,
        0.233,
        -3.491,
        0.467,
        -4,
        0.7,
        -4,
        0,
        1.483,
        10,
        0,
        2.917,
        -5,
        1,
        3.078,
        -5,
        3.239,
        -2.663,
        3.4,
        0
      ]
    },
    {
      "Target": "Parameter",
      "Id": "Param_Angle_Rotation92",
      "FadeInTime": -1.0,
      "FadeOutTime": -1.0,
      "Segments": [
        0,
        0,
        1,
        0.233,
        -5.153,
        0.467,
        -6,
        0.7,
        -6,
        0,
        1.483,
        10,
        0,
        2.917,
        -6,
        0,
        3.4,
        0
      ]
    },
    {
      "Target": "Parameter",
      "Id": "Param_Angle_Rotation68",
      "FadeInTime": -1.0,
      "FadeOutTime": -1.0,
      "Segments": [
        0,
        0,
        0,
        0.95,
        -10,
        0,
        1.917,
        1,
        0,
        2.717,
        -5,
        0,
        3.4,
        0
      ]
    },
    {
      "Target": "Parameter",
      "Id": "Param_Angle_Rotation69",
      "FadeInTime": -1.0,
      "FadeOutTime": -1.0,
      "Segments": [
        0,
        0,
        1,
        0.317,
        -5.173,
        0.633,
        -10,
        0.95,
        -10,
        0,
        1.917,
        1,
        0,
        2.717,
        -10,
        0,
        3.4,
        0
      ]
    },
    {
      "Target": "Parameter",
      "Id": "Param_Angle_Rotation77",
      "FadeInTime": -1.0,
      "FadeOutTime": -1.0,
      "Segments": [
        0,
        0,
        0,
        0.95,
        -4,
        0,
        1.917,
        3,
        0,
        2.717,
        -2,
        0,
        3.4,
        0
      ]
    },
    {
      "Target": "Parameter",
      "Id": "Param_Angle_Rotation78",
      "FadeInTime": -1.0,
      "FadeOutTime": -1.0,
      "Segments": [
        0,
        0,
        1,
        0.317,
        -5.913,
        0.633,
        -10,
        0.95,
        -10,
        0,
        1.917,
        4,
        0,
        2.717,
        -6,
        0,
        3.4,
        0
      ]
    },
    {
      "Target": "Parameter",
      "Id": "Param_Angle_Rotation71",
      "FadeInTime": -1.0,
      "FadeOutTime": -1.0,
      "Segments": [
        0,
        0,
        0,
        0.95,
        -10,
        0,
        1.917,
        10,
        0,
        2.717,
        -6,
        0,
        3.4,
        0
      ]
    },
    {
      "Target": "Parameter",
      "Id": "Param_Angle_Rotation72",
      "FadeInTime": -1.0,
      "FadeOutTime": -1.0,
      "Segments": [
        0,
        0,
        0,
        0.95,
        10,
        0,
        1.917,
        10,
        0,
        2.717,
        -6,
        1,
        2.945,
        -6,
        3.172,
        -3.66,
        3.4,
        0
      ]
    },
    {
      "Target": "Parameter",
      "Id": "Param_Angle_Rotation97",
      "FadeInTime": -1.0,
      "FadeOutTime": -1.0,
      "Segments": [
        0,
        0,
        0,
        0.95,
        -6,
        0,
        1.917,
        0,
        0,
        2.717,
        -6,
        0,
        3.4,
        0
      ]
    },
    {
      "Target": "Parameter",
      "Id": "Param_Angle_Rotation98",
      "FadeInTime": -1.0,
      "FadeOutTime": -1.0,
      "Segments": [
        0,
        0,
        0,
        1.917,
        0,
        0,
        3.4,
        0
      ]
    },
    {
      "Target": "Parameter",
      "Id": "Param_Angle_Rotation141",
      "FadeInTime": -1.0,
      "FadeOutTime": -1.0,
      "Segments": [
        0,
        0,
        0,
        0.95,
        -3,
        0,
        1.917,
        0,
        0,
        2.717,
        -3,
        0,
        3.4,
        0
      ]
    },
    {
      "Target": "Parameter",
      "Id": "Param_Angle_Rotation142",
      "FadeInTime": -1.0,
      "FadeOutTime": -1.0,
      "Segments": [
        0,
        0,
        0,
        0.95,
        -7,
        0,
        1.917,
        0,
        0,
        2.717,
        -7,
        0,
        3.4,
        0
      ]
    },
    {
      "Target": "Parameter",
      "Id": "Param_Angle_Rotation143",
      "FadeInTime": -1.0,
      "FadeOutTime": -1.0,
      "Segments": [
        0,
        0.04,
        1,
        0.317,
        -6.567,
        0.633,
        -10,
        0.95,
        -10,
        1,
        1.272,
        -10,
        1.595,
        -7.879,
        1.917,
        0,
        1,
        2.045,
        3.125,
        2.172,
        9,
        2.3,
        9,
        0,
        2.717,
        -4,
        1,
        2.945,
        -4,
        3.172,
        -3.432,
        3.4,
        0.04
      ]
    },
    {
      "Target": "Parameter",
      "Id": "Param_Angle_Rotation144",
      "FadeInTime": -1.0,
      "FadeOutTime": -1.0,
      "Segments": [
        0,
        0,
        1,
        0.317,
        -9.809,
        0.633,
        -16,
        0.95,
        -16,
        1,
        1.272,
        -16,
        1.595,
        -9.902,
        1.917,
        0,
        1,
        2.045,
        3.927,
        2.172,
        5,
        2.3,
        5,
        0,
        2.717,
        -13,
        1,
        2.945,
        -13,
        3.172,
        -8.005,
        3.4,
        0
      ]
    },
    {
      "Target": "Parameter",
      "Id": "Param_Angle_Rotation145",
      "FadeInTime": -1.0,
      "FadeOutTime": -1.0,
      "Segments": [
        0,
        0,
        0,
        0.95,
        -8,
        0,
        1.917,
        0,
        0,
        2.717,
        -8,
        0,
        3.4,
        0
      ]
    },
    {
      "Target": "Parameter",
      "Id": "Param_Angle_Rotation146",
      "FadeInTime": -1.0,
      "FadeOutTime": -1.0,
      "Segments": [
        0,
        0,
        1,
        0.317,
        -5.8,
        0.633,
        -11,
        0.95,
        -11,
        1,
        1.272,
        -11,
        1.595,
        -7.149,
        1.917,
        0,
        1,
        2.045,
        2.835,
        2.172,
        4,
        2.3,
        4,
        0,
        2.717,
        -11,
        0,
        3.4,
        0
      ]
    },
    {
      "Target": "Parameter",
      "Id": "Param_Angle_Rotation147",
      "FadeInTime": -1.0,
      "FadeOutTime": -1.0,
      "Segments": [
        0,
        0,
        1,
        0.317,
        -9.129,
        0.633,
        -12,
        0.95,
        -12,
        1,
        1.272,
        -12,
        1.595,
        -9.563,
        1.917,
        0,
        1,
        2.045,
        3.792,
        2.172,
        12,
        2.3,
        12,
        0,
        2.717,
        -12,
        0,
        3.4,
        0
      ]
    },
    {
      "Target": "Parameter",
      "Id": "Param_Angle_Rotation148",
      "FadeInTime": -1.0,
      "FadeOutTime": -1.0,
      "Segments": [
        0,
        0,
        0,
        0.95,
        -5,
        0,
        1.917,
        0,
        0,
        2.717,
        -6,
        0,
        3.4,
        0
      ]
    },
    {
      "Target": "Parameter",
      "Id": "Param_Angle_Rotation149",
      "FadeInTime": -1.0,
      "FadeOutTime": -1.0,
      "Segments": [
        0,
        0,
        0,
        0.95,
        -8,
        0,
        1.917,
        0,
        0,
        2.717,
        -2,
        0,
        3.4,
        0
      ]
    },
    {
      "Target": "Parameter",
      "Id": "Param_Angle_Rotation150",
      "FadeInTime": -1.0,
      "FadeOutTime": -1.0,
      "Segments": [
        0,
        0,
        1,
        0.317,
        -9.232,
        0.633,
        -16,
        0.95,
        -16,
        1,
        1.272,
        -16,
        1.595,
        -11.323,
        1.917,
        0,
        1,
        2.045,
        4.49,
        2.172,
        8,
        2.3,
        8,
        0,
        2.717,
        -11,
        0,
        3.4,
        0
      ]
    },
    {
      "Target": "Parameter",
      "Id": "Param_Angle_Rotation151",
      "FadeInTime": -1.0,
      "FadeOutTime": -1.0,
      "Segments": [
        0,
        0,
        1,
        0.317,
        -10.304,
        0.633,
        -20,
        0.95,
        -20,
        1,
        1.272,
        -20,
        1.595,
        -15.108,
        1.917,
        0,
        1,
        2.045,
        5.991,
        2.172,
        14,
        2.3,
        14,
        0,
        2.717,
        -7,
        0,
        3.4,
        0
      ]
    },
    {
      "Target": "Parameter",
      "Id": "Param12",
      "FadeInTime": -1.0,
      "FadeOutTime": -1.0,
      "Segments": [
        0,
        0,
        1,
        0.206,
        0,
        0.411,
        -0.445,
        0.617,
        -0.7,
        1,
        0.845,
        -0.982,
        1.072,
        -1,
        1.3,
        -1,
        0,
        2.85,
        -1,
        0,
        3.4,
        0
      ]
    },
    {
      "Target": "Parameter",
      "Id": "Param46",
      "FadeInTime": -1.0,
      "FadeOutTime": -1.0,
      "Segments": [
        0,
        0,
        0,
        2.85,
        7,
        0,
        3.4,
        0
      ]
    },
    {
      "Target": "Parameter",
      "Id": "Param_Angle_Rotation159",
      "FadeInTime": -1.0,
      "FadeOutTime": -1.0,
      "Segments": [
        0,
        0,
        0,
        0.95,
        -11,
        0,
        1.917,
        -5,
        0,
        2.617,
        -6,
        0,
        3.4,
        0
      ]
    },
    {
      "Target": "Parameter",
      "Id": "Param_Angle_Rotation160",
      "FadeInTime": -1.0,
      "FadeOutTime": -1.0,
      "Segments": [
        0,
        0,
        0,
        0.95,
        -7,
        0,
        1.917,
        3,
        0,
        2.617,
        -2,
        0,
        3.4,
        0
      ]
    },
    {
      "Target": "Parameter",
      "Id": "Param_Angle_Rotation161",
      "FadeInTime": -1.0,
      "FadeOutTime": -1.0,
      "Segments": [
        0,
        0,
        1,
        0.317,
        3.989,
        0.633,
        6.249,
        0.95,
        8,
        1,
        1.272,
        9.782,
        1.595,
        10,
        1.917,
        10,
        1,
        2.411,
        10,
        2.906,
        7.747,
        3.4,
        0
      ]
    },
    {
      "Target": "Parameter",
      "Id": "Param_Angle_Rotation162",
      "FadeInTime": -1.0,
      "FadeOutTime": -1.0,
      "Segments": [
        0,
        0,
        0,
        0.617,
        0,
        0,
        1.3,
        -12,
        0,
        2.517,
        7,
        0,
        3.4,
        0
      ]
    },
    {
      "Target": "Parameter",
      "Id": "Param_Angle_Rotation163",
      "FadeInTime": -1.0,
      "FadeOutTime": -1.0,
      "Segments": [
        0,
        0,
        0,
        3.4,
        0
      ]
    },
    {
      "Target": "Parameter",
      "Id": "Param_Angle_Rotation164",
      "FadeInTime": -1.0,
      "FadeOutTime": -1.0,
      "Segments": [
        0,
        0,
        0,
        3.4,
        0
      ]
    },
    {
      "Target": "Parameter",
      "Id": "Param_Angle_Rotation169",
      "FadeInTime": -1.0,
      "FadeOutTime": -1.0,
      "Segments": [
        0,
        0,
        0,
        0.6,
        0,
        0,
        1.3,
        -9,
        1,
        1.561,
        -9,
        1.822,
        -3.147,
        2.083,
        -2,
        1,
        2.522,
        -0.072,
        2.961,
        0,
        3.4,
        0
      ]
    },
    {
      "Target": "Parameter",
      "Id": "Param_Angle_Rotation170",
      "FadeInTime": -1.0,
      "FadeOutTime": -1.0,
      "Segments": [
        0,
        0,
        0,
        2.733,
        6.6,
        0,
        3.4,
        0
      ]
    },
    {
      "Target": "Parameter",
      "Id": "Param_Angle_Rotation171",
      "FadeInTime": -1.0,
      "FadeOutTime": -1.0,
      "Segments": [
        0,
        0,
        1,
        0.15,
        -2.061,
        0.3,
        -2.313,
        0.45,
        -4,
        1,
        0.5,
        -4.562,
        0.55,
        -9,
        0.6,
        -9,
        1,
        0.833,
        -9,
        1.067,
        3.151,
        1.3,
        4.68,
        1,
        1.883,
        8.502,
        2.467,
        9,
        3.05,
        9,
        1,
        3.167,
        9,
        3.283,
        1.603,
        3.4,
        0
      ]
    },
    {
      "Target": "Parameter",
      "Id": "Param_Angle_Rotation172",
      "FadeInTime": -1.0,
      "FadeOutTime": -1.0,
      "Segments": [
        0,
        0,
        1,
        0.2,
        -14.154,
        0.4,
        -20,
        0.6,
        -20,
        1,
        0.833,
        -20,
        1.067,
        -20.429,
        1.3,
        -12.02,
        1,
        1.778,
        5.199,
        2.255,
        25,
        2.733,
        25,
        1,
        2.955,
        25,
        3.178,
        15.727,
        3.4,
        0
      ]
    },
    {
      "Target": "Parameter",
      "Id": "Param25",
      "FadeInTime": -1.0,
      "FadeOutTime": -1.0,
      "Segments": [
        0,
        -1,
        0,
        1.3,
        -1,
        0,
        1.633,
        -1,
        0,
        2.517,
        1,
        0,
        2.533,
        -1,
        0,
        3.4,
        -1
      ]
    },
    {
      "Target": "Parameter",
      "Id": "Param36",
      "FadeInTime": -1.0,
      "FadeOutTime": -1.0,
      "Segments": [
        0,
        -1,
        1,
        0.433,
        -1,
        0.867,
        -0.857,
        1.3,
        -0.4,
        1,
        1.411,
        -0.283,
        1.522,
        0,
        1.633,
        0,
        0,
        3.4,
        -1
      ]
    },
    {
      "Target": "Parameter",
      "Id": "Param49",
      "FadeInTime": -1.0,
      "FadeOutTime": -1.0,
      "Segments": [
        0,
        0,
        0,
        3.4,
        0
      ]
    },
    {
      "Target": "Parameter",
      "Id": "Param50",
      "FadeInTime": -1.0,
      "FadeOutTime": -1.0,
      "Segments": [
        0,
        -1,
        0,
        0.833,
        -1,
        0,
        1.3,
        1,
        0,
        1.633,
        1,
        0,
        2.517,
        -1,
        0,
        3.4,
        -1
      ]
    },
    {
      "Target": "Parameter",
      "Id": "Param27",
      "FadeInTime": -1.0,
      "FadeOutTime": -1.0,
      "Segments": [
        0,
        0,
        0,
        0.6,
        -1,
        0,
        1.3,
        0,
        0,
        2.017,
        0,
        0,
        3.4,
        0
      ]
    },
    {
      "Target": "Parameter",
      "Id": "Param30",
      "FadeInTime": -1.0,
      "FadeOutTime": -1.0,
      "Segments": [
        0,
        -1,
        0,
        0.6,
        -1,
        0,
        1.3,
        1,
        0,
        2.017,
        -1,
        0,
        3.4,
        -1
      ]
    },
    {
      "Target": "Parameter",
      "Id": "Param28",
      "FadeInTime": -1.0,
      "FadeOutTime": -1.0,
      "Segments": [
        0,
        0,
        0,
        0.6,
        0,
        0,
        1.3,
        1,
        0,
        2.017,
        0,
        0,
        3.4,
        0
      ]
    },
    {
      "Target": "Parameter",
      "Id": "Param31",
      "FadeInTime": -1.0,
      "FadeOutTime": -1.0,
      "Segments": [
        0,
        -1,
        0,
        0.6,
        -1,
        0,
        1.3,
        -1,
        0,
        2.017,
        -1,
        0,
        3.017,
        -1,
        0,
        3.4,
        -1
      ]
    },
    {
      "Target": "Parameter",
      "Id": "Param29",
      "FadeInTime": -1.0,
      "FadeOutTime": -1.0,
      "Segments": [
        0,
        0,
        0,
        0.6,
        0,
        0,
        1.3,
        1,
        0,
        2.017,
        0,
        0,
        3.4,
        0
      ]
    },
    {
      "Target": "Parameter",
      "Id": "Param32",
      "FadeInTime": -1.0,
      "FadeOutTime": -1.0,
      "Segments": [
        0,
        -1,
        0,
        0.6,
        -1,
        0,
        1.3,
        1,
        0,
        2.017,
        -1,
        0,
        3.4,
        -1
      ]
    },
    {
      "Target": "Parameter",
      "Id": "Param_Angle_Rotation165",
      "FadeInTime": -1.0,
      "FadeOutTime": -1.0,
      "Segments": [
        0,
        0,
        0,
        0.6,
        2.28,
        0,
        1.3,
        -4.92,
        0,
        2.1,
        2.28,
        0,
        3.4,
        0
      ]
    },
    {
      "Target": "Parameter",
      "Id": "Param_Angle_Rotation166",
      "FadeInTime": -1.0,
      "FadeOutTime": -1.0,
      "Segments": [
        0,
        0,
        1,
        0.2,
        -1.354,
        0.4,
        -1.022,
        0.6,
        -2.34,
        1,
        0.833,
        -3.877,
        1.067,
        -8.04,
        1.3,
        -8.04,
        1,
        1.567,
        -8.04,
        1.833,
        -7.222,
        2.1,
        -2.34,
        1,
        2.311,
        1.525,
        2.522,
        6.823,
        2.733,
        6.823,
        1,
        2.955,
        6.823,
        3.178,
        1.505,
        3.4,
        0
      ]
    },
    {
      "Target": "Parameter",
      "Id": "Param_Angle_Rotation173",
      "FadeInTime": -1.0,
      "FadeOutTime": -1.0,
      "Segments": [
        0,
        0,
        1,
        0.2,
        -7.376,
        0.4,
        -10.44,
        0.6,
        -10.44,
        0,
        1.3,
        12.6,
        0,
        2.1,
        -10.44,
        0,
        2.733,
        13,
        1,
        2.955,
        13,
        3.178,
        8.196,
        3.4,
        0
      ]
    },
    {
      "Target": "Parameter",
      "Id": "Param_Angle_Rotation174",
      "FadeInTime": -1.0,
      "FadeOutTime": -1.0,
      "Segments": [
        0,
        0,
        1,
        0.2,
        -8.921,
        0.4,
        -10.26,
        0.6,
        -10.26,
        0,
        1.3,
        29.94,
        0,
        2.1,
        -10.26,
        0,
        2.733,
        21,
        1,
        2.955,
        21,
        3.178,
        9.912,
        3.4,
        0
      ]
    },
    {
      "Target": "Parameter",
      "Id": "Param41",
      "FadeInTime": -1.0,
      "FadeOutTime": -1.0,
      "Segments": [
        0,
        0,
        0,
        0.6,
        -5.58,
        0,
        1.3,
        1.92,
        0,
        2.1,
        -5.58,
        0,
        3.4,
        0
      ]
    },
    {
      "Target": "Parameter",
      "Id": "Param42",
      "FadeInTime": -1.0,
      "FadeOutTime": -1.0,
      "Segments": [
        0,
        0,
        0,
        0.6,
        5.16,
        0,
        1.3,
        -1.32,
        0,
        2.1,
        5.16,
        0,
        3.4,
        0
      ]
    },
    {
      "Target": "Parameter",
      "Id": "Param_Angle_Rotation152",
      "FadeInTime": -1.0,
      "FadeOutTime": -1.0,
      "Segments": [
        0,
        0,
        0,
        0.95,
        -5,
        0,
        1.633,
        -5,
        0,
        2.717,
        -5,
        0,
        3.4,
        0
      ]
    },
    {
      "Target": "Parameter",
      "Id": "Param_Angle_Rotation153",
      "FadeInTime": -1.0,
      "FadeOutTime": -1.0,
      "Segments": [
        0,
        0,
        0,
        0.95,
        -17,
        0,
        1.633,
        10,
        1,
        1.816,
        10,
        2,
        -3.718,
        2.183,
        -16,
        1,
        2.361,
        -27.91,
        2.539,
        -30,
        2.717,
        -30,
        0,
        3.4,
        0
      ]
    },
    {
      "Target": "Parameter",
      "Id": "Param_Angle_Rotation154",
      "FadeInTime": -1.0,
      "FadeOutTime": -1.0,
      "Segments": [
        0,
        0,
        0,
        0.95,
        -8,
        1,
        1.178,
        -8,
        1.405,
        3.756,
        1.633,
        17,
        1,
        1.816,
        27.66,
        2,
        29.89,
        2.183,
        29.89,
        0,
        2.717,
        -23,
        0,
        3.4,
        0
      ]
    },
    {
      "Target": "Parameter",
      "Id": "Param_Angle_Rotation155",
      "FadeInTime": -1.0,
      "FadeOutTime": -1.0,
      "Segments": [
        0,
        0,
        1,
        0.317,
        -6.046,
        0.633,
        -8.79,
        0.95,
        -14.762,
        1,
        1.178,
        -19.059,
        1.405,
        -24,
        1.633,
        -24,
        0,
        2.183,
        29.836,
        0,
        2.717,
        -28,
        0,
        3.4,
        0
      ]
    },
    {
      "Target": "Parameter",
      "Id": "Param_Angle_Rotation156",
      "FadeInTime": -1.0,
      "FadeOutTime": -1.0,
      "Segments": [
        0,
        0,
        0,
        0.95,
        -11,
        0,
        1.633,
        2,
        1,
        1.816,
        2,
        2,
        -1.9,
        2.183,
        -9,
        1,
        2.361,
        -15.884,
        2.539,
        -19,
        2.717,
        -19,
        0,
        3.4,
        0
      ]
    },
    {
      "Target": "Parameter",
      "Id": "Param_Angle_Rotation157",
      "FadeInTime": -1.0,
      "FadeOutTime": -1.0,
      "Segments": [
        0,
        0,
        0,
        0.95,
        -17,
        0,
        1.633,
        12,
        1,
        1.816,
        12,
        2,
        11.356,
        2.183,
        3,
        1,
        2.361,
        -5.103,
        2.539,
        -19,
        2.717,
        -19,
        0,
        3.4,
        0
      ]
    },
    {
      "Target": "Parameter",
      "Id": "Param_Angle_Rotation158",
      "FadeInTime": -1.0,
      "FadeOutTime": -1.0,
      "Segments": [
        0,
        0,
        1,
        0.317,
        -12.913,
        0.633,
        -22,
        0.95,
        -22,
        1,
        1.178,
        -22,
        1.405,
        -19.659,
        1.633,
        -10,
        1,
        1.816,
        -2.225,
        2,
        6,
        2.183,
        6,
        0,
        2.717,
        -23,
        0,
        3.4,
        0
      ]
    },
    {
      "Target": "Parameter",
      "Id": "Param_Angle_Rotation175",
      "FadeInTime": -1.0,
      "FadeOutTime": -1.0,
      "Segments": [
        0,
        0,
        0,
        0.95,
        -23,
        1,
        1.178,
        -23,
        1.405,
        -22.559,
        1.633,
        -13,
        1,
        1.816,
        -5.306,
        2,
        17,
        2.183,
        17,
        0,
        2.717,
        -6,
        0,
        3.4,
        0
      ]
    }
  ],
  "UserData": []
}