{
  "Version": 3,
  "Meta": {
    "Duration": 10.5,
    "Fps": 30.0,
    "Loop": true,
    "AreBeziersRestricted": true,
    "FadeInTime": 0.9,
    "FadeOutTime": 0.9,
    "CurveCount": 185,
    "TotalSegmentCount": 1507,
    "TotalPointCount": 1962,
    "UserDataCount": 0,
    "TotalUserDataSize": 0
  },
  "Curves": [
    {
      "Target": "Parameter",
      "Id": "Param49",
      "FadeInTime": -1.0,
      "FadeOutTime": -1.0,
      "Segments": [
        0,
        0,
        0,
        0.667,
        0,
        0,
        1,
        0,
        1,
        1.389,
        0,
        1.778,
        4.997,
        2.167,
        5,
        1,
        2.5,
        5.003,
        2.834,
        5.002,
        3.167,
        5.004,
        0,
        3.333,
        5.06,
        1,
        4.333,
        5.06,
        5.333,
        3.855,
        6.333,
        1.18,
        1,
        6.5,
        0.734,
        6.666,
        0.34,
        6.833,
        0.34,
        0,
        7.333,
        0.34,
        0,
        8,
        0.34,
        0,
        9.167,
        0.34,
        0,
        10.5,
        0
      ]
    },
    {
      "Target": "Parameter",
      "Id": "Param87",
      "FadeInTime": -1.0,
      "FadeOutTime": -1.0,
      "Segments": [
        0,
        0,
        0,
        0.667,
        0,
        0,
        1,
        0,
        0,
        2.167,
        -5,
        0,
        3.167,
        -5,
        0,
        3.333,
        -5.3,
        0,
        6.333,
        -4,
        0,
        6.833,
        -4,
        0,
        7.333,
        -4,
        0,
        8,
        -4,
        0,
        9.167,
        -4,
        0,
        10.5,
        0
      ]
    },
    {
      "Target": "Parameter",
      "Id": "Param50",
      "FadeInTime": -1.0,
      "FadeOutTime": -1.0,
      "Segments": [
        0,
        0,
        0,
        0.667,
        0,
        0,
        1.333,
        0,
        0,
        2.167,
        0,
        1,
        2.5,
        0,
        2.834,
        8.325,
        3.167,
        17.441,
        1,
        3.222,
        18.96,
        3.278,
        18.46,
        3.333,
        18.46,
        1,
        3.833,
        18.46,
        4.333,
        17.978,
        4.833,
        15.98,
        1,
        5.089,
        14.959,
        5.344,
        13.023,
        5.6,
        10.805,
        1,
        5.844,
        8.683,
        6.089,
        3.988,
        6.333,
        1.71,
        1,
        6.5,
        0.157,
        6.666,
        0,
        6.833,
        0,
        0,
        7.333,
        0,
        0,
        8,
        0,
        0,
        9.167,
        0,
        0,
        10.5,
        0
      ]
    },
    {
      "Target": "Parameter",
      "Id": "Param89",
      "FadeInTime": -1.0,
      "FadeOutTime": -1.0,
      "Segments": [
        0,
        0,
        0,
        0.667,
        0,
        0,
        2.167,
        0,
        0,
        3.333,
        0,
        0,
        6.333,
        2,
        0,
        6.833,
        2,
        0,
        7.333,
        2,
        0,
        8,
        2,
        0,
        9.167,
        2,
        0,
        10.5,
        0
      ]
    },
    {
      "Target": "Parameter",
      "Id": "Param90",
      "FadeInTime": -1.0,
      "FadeOutTime": -1.0,
      "Segments": [
        0,
        0,
        0,
        0.667,
        0,
        0,
        1.433,
        0,
        0,
        3.333,
        0,
        0,
        6.333,
        0,
        0,
        6.833,
        0,
        0,
        7.333,
        0,
        0,
        8,
        0,
        0,
        9.167,
        0,
        0,
        10.5,
        0
      ]
    },
    {
      "Target": "Parameter",
      "Id": "Param52",
      "FadeInTime": -1.0,
      "FadeOutTime": -1.0,
      "Segments": [
        0,
        0,
        0,
        0.667,
        0,
        0,
        1.533,
        0,
        0,
        3.333,
        0,
        0,
        6.333,
        0,
        0,
        6.833,
        0,
        0,
        7.333,
        0,
        0,
        8,
        0,
        0,
        9.167,
        0,
        0,
        10.5,
        0
      ]
    },
    {
      "Target": "Parameter",
      "Id": "Param53",
      "FadeInTime": -1.0,
      "FadeOutTime": -1.0,
      "Segments": [
        0,
        0,
        0,
        0.667,
        0,
        0,
        1.667,
        -3,
        0,
        2.333,
        0,
        0,
        3.333,
        0,
        0,
        6.333,
        0,
        0,
        6.833,
        0,
        0,
        7.333,
        0,
        0,
        8,
        0,
        0,
        9.167,
        0,
        0,
        10.5,
        0
      ]
    },
    {
      "Target": "Parameter",
      "Id": "Param54",
      "FadeInTime": -1.0,
      "FadeOutTime": -1.0,
      "Segments": [
        0,
        0,
        0,
        0.667,
        0,
        0,
        1.833,
        -5,
        0,
        2.5,
        0,
        0,
        3.333,
        0,
        0,
        6.333,
        0,
        0,
        6.833,
        6,
        0,
        7.333,
        -4,
        0,
        8,
        6,
        0,
        9.167,
        -4,
        0,
        10.5,
        0
      ]
    },
    {
      "Target": "Parameter",
      "Id": "Param55",
      "FadeInTime": -1.0,
      "FadeOutTime": -1.0,
      "Segments": [
        0,
        0,
        0,
        0.333,
        4,
        0,
        1,
        -4,
        1,
        1.333,
        -4,
        1.667,
        -3.276,
        2,
        0,
        1,
        2.222,
        2.184,
        2.445,
        5,
        2.667,
        5,
        0,
        3.333,
        0,
        0,
        6.333,
        0,
        0,
        7.1,
        9,
        0,
        7.667,
        -10,
        0,
        8.5,
        9,
        0,
        9.667,
        -4,
        0,
        10.5,
        0
      ]
    },
    {
      "Target": "Parameter",
      "Id": "Param88",
      "FadeInTime": -1.0,
      "FadeOutTime": -1.0,
      "Segments": [
        0,
        0,
        0,
        0.167,
        -30,
        0,
        0.667,
        14,
        1,
        0.889,
        14,
        1.111,
        10.276,
        1.333,
        0,
        1,
        1.611,
        -12.846,
        1.889,
        -21,
        2.167,
        -21,
        0,
        2.833,
        9,
        0,
        3.167,
        0,
        0,
        3.333,
        11,
        1,
        3.555,
        11,
        3.778,
        -7.276,
        4,
        -10,
        1,
        4.778,
        -19.532,
        5.555,
        -21.72,
        6.333,
        -21.72,
        0,
        7.333,
        14,
        0,
        8,
        -21.72,
        0,
        8.833,
        14,
        0,
        10,
        -13,
        0,
        10.5,
        0
      ]
    },
    {
      "Target": "Parameter",
      "Id": "Param51",
      "FadeInTime": -1.0,
      "FadeOutTime": -1.0,
      "Segments": [
        0,
        0,
        0,
        0.667,
        0,
        0,
        1.333,
        0,
        0,
        2.167,
        0,
        0,
        3,
        16,
        1,
        3.056,
        16,
        3.111,
        3.533,
        3.167,
        0,
        1,
        3.222,
        -3.533,
        3.278,
        -6.424,
        3.333,
        -6.84,
        1,
        3.555,
        -8.504,
        3.778,
        -9.932,
        4,
        -11,
        1,
        4.778,
        -14.737,
        5.555,
        -16.26,
        6.333,
        -16.26,
        0,
        6.5,
        30,
        0,
        7.5,
        -15,
        0,
        8.167,
        10,
        0,
        9,
        -15,
        0,
        10.167,
        0,
        0,
        10.5,
        0
      ]
    },
    {
      "Target": "Parameter",
      "Id": "Param91",
      "FadeInTime": -1.0,
      "FadeOutTime": -1.0,
      "Segments": [
        0,
        0,
        0,
        0.667,
        0,
        0,
        1.333,
        0,
        0,
        2.167,
        0,
        0,
        3.333,
        0,
        0,
        6.333,
        0,
        0,
        6.833,
        0,
        0,
        7.333,
        0,
        0,
        8,
        0,
        0,
        9.167,
        0,
        0,
        10.5,
        0
      ]
    },
    {
      "Target": "Parameter",
      "Id": "Param96",
      "FadeInTime": -1.0,
      "FadeOutTime": -1.0,
      "Segments": [
        0,
        0,
        0,
        0.167,
        30,
        0,
        0.5,
        -30,
        0,
        0.667,
        0,
        0,
        1,
        0,
        0,
        1.333,
        30,
        0,
        2.167,
        30,
        0,
        2.5,
        0,
        0,
        3.333,
        0,
        0,
        4,
        -30,
        0,
        6.417,
        -30,
        0,
        6.583,
        13,
        0,
        6.75,
        -6,
        0,
        7.333,
        0,
        0,
        8,
        0,
        0,
        9.167,
        0,
        0,
        10.5,
        0
      ]
    },
    {
      "Target": "Parameter",
      "Id": "Param97",
      "FadeInTime": -1.0,
      "FadeOutTime": -1.0,
      "Segments": [
        0,
        0,
        0,
        0.333,
        30,
        0,
        0.667,
        -30,
        0,
        1,
        -30,
        0,
        1.333,
        30,
        0,
        2.167,
        30,
        0,
        2.5,
        0,
        0,
        3.333,
        0,
        0,
        4,
        -30,
        0,
        6.333,
        0,
        0,
        6.833,
        0,
        0,
        7.333,
        0,
        0,
        8,
        0,
        0,
        9.167,
        0,
        0,
        10.5,
        0
      ]
    },
    {
      "Target": "Parameter",
      "Id": "ParamEyeROpen",
      "FadeInTime": -1.0,
      "FadeOutTime": -1.0,
      "Segments": [
        0,
        1,
        0,
        0.333,
        0,
        1,
        0.555,
        0,
        0.778,
        0.57,
        1,
        0.719,
        1,
        1.389,
        0.98,
        1.778,
        1,
        2.167,
        1,
        0,
        2.5,
        0,
        0,
        2.833,
        1,
        0,
        3.333,
        1,
        0,
        3.667,
        0,
        0,
        4,
        0,
        0,
        6.333,
        0,
        0,
        6.833,
        0,
        0,
        7.333,
        0,
        0,
        8,
        0,
        0,
        9.167,
        1,
        0,
        9.833,
        0,
        0,
        10.5,
        1
      ]
    },
    {
      "Target": "Parameter",
      "Id": "ParamEyeRSmile",
      "FadeInTime": -1.0,
      "FadeOutTime": -1.0,
      "Segments": [
        0,
        0,
        0,
        0.333,
        0,
        0,
        1,
        0,
        0,
        2.167,
        0,
        0,
        3.333,
        0,
        0,
        3.667,
        1,
        0,
        4,
        1,
        0,
        6.333,
        1,
        0,
        6.833,
        1,
        0,
        7.333,
        1,
        0,
        8,
        1,
        0,
        9.167,
        0,
        0,
        10.5,
        0
      ]
    },
    {
      "Target": "Parameter",
      "Id": "ParamEyeLOpen",
      "FadeInTime": -1.0,
      "FadeOutTime": -1.0,
      "Segments": [
        0,
        1,
        0,
        0.333,
        0,
        1,
        0.555,
        0,
        0.778,
        0.57,
        1,
        0.719,
        1,
        1.389,
        0.98,
        1.778,
        1,
        2.167,
        1,
        0,
        2.5,
        0,
        0,
        2.833,
        1,
        0,
        3.333,
        1,
        0,
        3.667,
        0,
        0,
        4,
        1,
        0,
        6.333,
        1,
        0,
        6.833,
        0,
        0,
        7.333,
        0,
        0,
        8,
        0,
        0,
        9.167,
        1,
        0,
        9.833,
        0,
        0,
        10.5,
        1
      ]
    },
    {
      "Target": "Parameter",
      "Id": "ParamEyeLSmile",
      "FadeInTime": -1.0,
      "FadeOutTime": -1.0,
      "Segments": [
        0,
        0,
        0,
        0.333,
        0,
        0,
        1,
        0,
        0,
        2.167,
        0,
        0,
        3.333,
        0,
        0,
        3.667,
        1,
        0,
        4,
        0,
        0,
        6.333,
        0,
        0,
        6.833,
        1,
        0,
        7.333,
        1,
        0,
        8,
        1,
        0,
        9.167,
        0,
        0,
        10.5,
        0
      ]
    },
    {
      "Target": "Parameter",
      "Id": "ParamEyeBallX",
      "FadeInTime": -1.0,
      "FadeOutTime": -1.0,
      "Segments": [
        0,
        0,
        0,
        0.333,
        0,
        1,
        0.555,
        0,
        0.778,
        -0.398,
        1,
        -0.503,
        1,
        1.389,
        -0.686,
        1.778,
        -0.7,
        2.167,
        -0.7,
        0,
        3.333,
        -0.7,
        0,
        6.333,
        -1,
        0,
        6.833,
        -1,
        0,
        7.333,
        -1,
        0,
        8,
        -1,
        0,
        9.167,
        -1,
        0,
        10.5,
        0
      ]
    },
    {
      "Target": "Parameter",
      "Id": "ParamEyeBallY",
      "FadeInTime": -1.0,
      "FadeOutTime": -1.0,
      "Segments": [
        0,
        0,
        0,
        0.333,
        0,
        0,
        1,
        0.575,
        1,
        1.389,
        0.575,
        1.778,
        0.305,
        2.167,
        0.2,
        1,
        2.556,
        0.095,
        2.944,
        0.1,
        3.333,
        0.1,
        0,
        6.333,
        0.5,
        0,
        6.833,
        0.5,
        0,
        7.333,
        0.5,
        0,
        8,
        0.5,
        0,
        9.167,
        0.5,
        0,
        10.5,
        0
      ]
    },
    {
      "Target": "Parameter",
      "Id": "ParamBrowRY",
      "FadeInTime": -1.0,
      "FadeOutTime": -1.0,
      "Segments": [
        0,
        0,
        0,
        0.333,
        0,
        0,
        1,
        0,
        0,
        2.167,
        0,
        0,
        3.333,
        0,
        0,
        4,
        -0.2,
        0,
        6.333,
        -0.2,
        0,
        6.833,
        -0.2,
        0,
        7.333,
        -0.2,
        0,
        8,
        -0.2,
        0,
        9.167,
        -0.2,
        0,
        10.5,
        0
      ]
    },
    {
      "Target": "Parameter",
      "Id": "ParamBrowRX",
      "FadeInTime": -1.0,
      "FadeOutTime": -1.0,
      "Segments": [
        0,
        0,
        0,
        0.333,
        0,
        0,
        1,
        0,
        0,
        2.167,
        0,
        0,
        3.333,
        0,
        0,
        6.333,
        0,
        0,
        6.833,
        0,
        0,
        7.333,
        0,
        0,
        8,
        0,
        0,
        9.167,
        0,
        0,
        10.5,
        0
      ]
    },
    {
      "Target": "Parameter",
      "Id": "ParamBrowRAngle",
      "FadeInTime": -1.0,
      "FadeOutTime": -1.0,
      "Segments": [
        0,
        0,
        0,
        0.333,
        0,
        0,
        1,
        0,
        0,
        2.167,
        0,
        0,
        3.333,
        0,
        0,
        6.333,
        0,
        0,
        6.833,
        0,
        0,
        7.333,
        0,
        0,
        8,
        0,
        0,
        9.167,
        0,
        0,
        10.5,
        0
      ]
    },
    {
      "Target": "Parameter",
      "Id": "ParamBrowRForm",
      "FadeInTime": -1.0,
      "FadeOutTime": -1.0,
      "Segments": [
        0,
        0,
        0,
        0.333,
        0,
        0,
        1,
        0,
        0,
        2.167,
        0,
        0,
        3.333,
        0,
        0,
        4,
        -1,
        0,
        6.333,
        -1,
        0,
        6.833,
        -1,
        0,
        7.333,
        -1,
        0,
        8,
        -1,
        0,
        9.167,
        -1,
        0,
        10.5,
        0
      ]
    },
    {
      "Target": "Parameter",
      "Id": "ParamBrowLY",
      "FadeInTime": -1.0,
      "FadeOutTime": -1.0,
      "Segments": [
        0,
        0,
        0,
        0.333,
        0,
        0,
        1,
        0,
        0,
        2.167,
        0,
        0,
        3.333,
        0,
        0,
        6.333,
        0,
        0,
        6.833,
        0,
        0,
        7.333,
        0,
        0,
        8,
        0,
        0,
        9.167,
        0,
        0,
        10.5,
        0
      ]
    },
    {
      "Target": "Parameter",
      "Id": "ParamBrowLX",
      "FadeInTime": -1.0,
      "FadeOutTime": -1.0,
      "Segments": [
        0,
        0,
        0,
        0.333,
        0,
        0,
        1,
        0,
        0,
        2.167,
        0,
        0,
        3.333,
        0,
        0,
        6.333,
        0,
        0,
        6.833,
        0,
        0,
        7.333,
        0,
        0,
        8,
        0,
        0,
        9.167,
        0,
        0,
        10.5,
        0
      ]
    },
    {
      "Target": "Parameter",
      "Id": "ParamBrowLAngle",
      "FadeInTime": -1.0,
      "FadeOutTime": -1.0,
      "Segments": [
        0,
        0,
        0,
        0.333,
        0,
        0,
        1,
        0,
        0,
        2.167,
        0,
        0,
        3.333,
        0,
        0,
        6.333,
        0,
        0,
        6.833,
        0,
        0,
        7.333,
        0,
        0,
        8,
        0,
        0,
        9.167,
        0,
        0,
        10.5,
        0
      ]
    },
    {
      "Target": "Parameter",
      "Id": "ParamBrowLForm",
      "FadeInTime": -1.0,
      "FadeOutTime": -1.0,
      "Segments": [
        0,
        0,
        0,
        0.333,
        0,
        0,
        1,
        0,
        0,
        2.167,
        0,
        0,
        3.333,
        0,
        0,
        4,
        -1,
        0,
        6.333,
        -1,
        0,
        6.833,
        -1,
        0,
        7.333,
        -1,
        0,
        8,
        -1,
        0,
        9.167,
        -1,
        0,
        10.5,
        0
      ]
    },
    {
      "Target": "Parameter",
      "Id": "ParamMouthForm",
      "FadeInTime": -1.0,
      "FadeOutTime": -1.0,
      "Segments": [
        0,
        1,
        1,
        0.111,
        1,
        0.222,
        0.195,
        0.333,
        0,
        1,
        0.555,
        -0.389,
        0.778,
        -0.431,
        1,
        -0.431,
        0,
        2.167,
        -0.431,
        0,
        3.333,
        -0.431,
        0,
        6.333,
        -0.431,
        0,
        6.833,
        -0.431,
        0,
        7.333,
        -0.431,
        0,
        8,
        -0.431,
        0,
        9.167,
        -0.431,
        0,
        10.5,
        1
      ]
    },
    {
      "Target": "Parameter",
      "Id": "ParamMouthOpenY",
      "FadeInTime": -1.0,
      "FadeOutTime": -1.0,
      "Segments": [
        0,
        0,
        0,
        0.333,
        0,
        0,
        1,
        0.288,
        0,
        2.167,
        0.288,
        0,
        3.333,
        0.288,
        0,
        6.333,
        0.9,
        0,
        6.833,
        0,
        0,
        7.333,
        0.7,
        0,
        8,
        0.7,
        0,
        9.167,
        0.7,
        0,
        10.5,
        0
      ]
    },
    {
      "Target": "Parameter",
      "Id": "ParamCheek",
      "FadeInTime": -1.0,
      "FadeOutTime": -1.0,
      "Segments": [
        0,
        0,
        0,
        0.333,
        0,
        0,
        1,
        0,
        0,
        2.167,
        0,
        0,
        3.333,
        0,
        0,
        6.333,
        0,
        0,
        6.833,
        0,
        0,
        7.333,
        0,
        0,
        8,
        0,
        0,
        9.167,
        0,
        0,
        10.5,
        0
      ]
    },
    {
      "Target": "Parameter",
      "Id": "ParamCheek2",
      "FadeInTime": -1.0,
      "FadeOutTime": -1.0,
      "Segments": [
        0,
        0,
        0,
        10.5,
        0
      ]
    },
    {
      "Target": "Parameter",
      "Id": "Param",
      "FadeInTime": -1.0,
      "FadeOutTime": -1.0,
      "Segments": [
        0,
        1,
        0,
        10.5,
        1
      ]
    },
    {
      "Target": "Parameter",
      "Id": "Param2",
      "FadeInTime": -1.0,
      "FadeOutTime": -1.0,
      "Segments": [
        0,
        1,
        0,
        10.5,
        1
      ]
    },
    {
      "Target": "Parameter",
      "Id": "ParamAngleX",
      "FadeInTime": -1.0,
      "FadeOutTime": -1.0,
      "Segments": [
        0,
        0,
        0,
        2.167,
        -20,
        0,
        3.333,
        0,
        0,
        6.333,
        -20,
        0,
        6.933,
        30,
        1,
        7.122,
        30,
        7.311,
        8.036,
        7.5,
        0,
        1,
        8.056,
        -23.635,
        8.611,
        -30,
        9.167,
        -30,
        0,
        10.5,
        0
      ]
    },
    {
      "Target": "Parameter",
      "Id": "ParamAngleY",
      "FadeInTime": -1.0,
      "FadeOutTime": -1.0,
      "Segments": [
        0,
        0,
        0,
        0.667,
        -20,
        1,
        1,
        -20,
        1.334,
        -1.997,
        1.667,
        -1.406,
        1,
        2.056,
        -0.717,
        2.444,
        -0.506,
        2.833,
        -0.265,
        1,
        3.222,
        -0.024,
        3.611,
        0,
        4,
        0,
        0,
        5,
        -15,
        0,
        6.167,
        17,
        0,
        6.667,
        0,
        0,
        7.1,
        15,
        0,
        7.667,
        0,
        1,
        7.945,
        0,
        8.222,
        7.716,
        8.5,
        15,
        1,
        8.944,
        26.655,
        9.389,
        30,
        9.833,
        30,
        0,
        10.5,
        0
      ]
    },
    {
      "Target": "Parameter",
      "Id": "ParamAngleZ",
      "FadeInTime": -1.0,
      "FadeOutTime": -1.0,
      "Segments": [
        0,
        0,
        0,
        0.667,
        -11,
        1,
        1,
        -11,
        1.334,
        8.965,
        1.667,
        14.407,
        1,
        2.056,
        20.755,
        2.444,
        20.533,
        2.833,
        20.533,
        1,
        3.222,
        20.533,
        3.611,
        9.451,
        4,
        0,
        1,
        4.333,
        -8.101,
        4.667,
        -9,
        5,
        -9,
        0,
        6.167,
        0,
        0,
        6.667,
        -17,
        0,
        7.1,
        -7,
        1,
        7.289,
        -7,
        7.478,
        -10.249,
        7.667,
        -11.219,
        1,
        7.945,
        -12.645,
        8.222,
        -12.701,
        8.5,
        -12.701,
        0,
        9.833,
        10,
        0,
        10.5,
        0
      ]
    },
    {
      "Target": "Parameter",
      "Id": "ParamBodyAngleX",
      "FadeInTime": -1.0,
      "FadeOutTime": -1.0,
      "Segments": [
        0,
        0,
        0,
        0.667,
        6,
        0,
        2.5,
        -10,
        0,
        3.667,
        5,
        0,
        6.5,
        -10,
        0,
        7,
        6,
        0,
        7.5,
        -5,
        0,
        8.167,
        4,
        0,
        9.433,
        0,
        0,
        10.5,
        0
      ]
    },
    {
      "Target": "Parameter",
      "Id": "ParamBodyAngleY",
      "FadeInTime": -1.0,
      "FadeOutTime": -1.0,
      "Segments": [
        0,
        0,
        0,
        0.333,
        -3,
        0,
        2.167,
        2,
        0,
        3.333,
        -5,
        1,
        3.555,
        -5,
        3.778,
        -4.738,
        4,
        -4,
        1,
        4.778,
        -1.415,
        5.555,
        0,
        6.333,
        0,
        0,
        6.833,
        0,
        0,
        7.333,
        0,
        0,
        8,
        0,
        0,
        9.167,
        0,
        0,
        10.5,
        0
      ]
    },
    {
      "Target": "Parameter",
      "Id": "ParamBodyAngleZ",
      "FadeInTime": -1.0,
      "FadeOutTime": -1.0,
      "Segments": [
        0,
        0,
        0,
        0.333,
        -2,
        0,
        2.167,
        1.077,
        0,
        3.333,
        -3,
        1,
        4.333,
        -3,
        5.333,
        -0.792,
        6.333,
        5,
        1,
        6.5,
        5.965,
        6.666,
        8,
        6.833,
        8,
        0,
        7.333,
        2,
        1,
        7.555,
        2,
        7.778,
        3.786,
        8,
        4.531,
        1,
        8.389,
        5.834,
        8.778,
        6.013,
        9.167,
        6.013,
        0,
        10.5,
        0
      ]
    },
    {
      "Target": "Parameter",
      "Id": "Param98",
      "FadeInTime": -1.0,
      "FadeOutTime": -1.0,
      "Segments": [
        0,
        0,
        0,
        1,
        0,
        0,
        3.333,
        0,
        1,
        4.333,
        0,
        5.333,
        1.282,
        6.333,
        5.22,
        1,
        6.5,
        5.876,
        6.666,
        10,
        6.833,
        10,
        0,
        7.333,
        10,
        0,
        8,
        10,
        0,
        9.167,
        10,
        0,
        10.5,
        0
      ]
    },
    {
      "Target": "Parameter",
      "Id": "ParamBreath",
      "FadeInTime": -1.0,
      "FadeOutTime": -1.0,
      "Segments": [
        0,
        0,
        0,
        0.333,
        0,
        0,
        1,
        0,
        0,
        2.167,
        0,
        0,
        3.333,
        0,
        0,
        6.333,
        0,
        0,
        6.833,
        0,
        0,
        7.333,
        0,
        0,
        8,
        0,
        0,
        9.167,
        0,
        0,
        10.5,
        0
      ]
    },
    {
      "Target": "Parameter",
      "Id": "Param116",
      "FadeInTime": -1.0,
      "FadeOutTime": -1.0,
      "Segments": [
        0,
        0,
        0,
        10.5,
        0
      ]
    },
    {
      "Target": "Parameter",
      "Id": "Param117",
      "FadeInTime": -1.0,
      "FadeOutTime": -1.0,
      "Segments": [
        0,
        0,
        0,
        10.5,
        0
      ]
    },
    {
      "Target": "Parameter",
      "Id": "Param118",
      "FadeInTime": -1.0,
      "FadeOutTime": -1.0,
      "Segments": [
        0,
        0,
        0,
        10.5,
        0
      ]
    },
    {
      "Target": "Parameter",
      "Id": "Param119",
      "FadeInTime": -1.0,
      "FadeOutTime": -1.0,
      "Segments": [
        0,
        0,
        0,
        10.5,
        0
      ]
    },
    {
      "Target": "Parameter",
      "Id": "Param120",
      "FadeInTime": -1.0,
      "FadeOutTime": -1.0,
      "Segments": [
        0,
        0,
        0,
        10.5,
        0
      ]
    },
    {
      "Target": "Parameter",
      "Id": "Param45",
      "FadeInTime": -1.0,
      "FadeOutTime": -1.0,
      "Segments": [
        0,
        0,
        0,
        1,
        0,
        0,
        3.333,
        0,
        0,
        6.333,
        0,
        0,
        6.833,
        0,
        0,
        7.333,
        0,
        0,
        8,
        0,
        0,
        9.167,
        0,
        0,
        10.5,
        0
      ]
    },
    {
      "Target": "Parameter",
      "Id": "Param43",
      "FadeInTime": -1.0,
      "FadeOutTime": -1.0,
      "Segments": [
        0,
        0,
        0,
        1,
        -16.99,
        0,
        3.333,
        0,
        0,
        6.333,
        -30,
        0,
        6.833,
        -16.99,
        0,
        7.333,
        -27,
        0,
        8,
        -21.64,
        0,
        9.167,
        -30,
        0,
        10.5,
        0
      ]
    },
    {
      "Target": "Parameter",
      "Id": "Param44",
      "FadeInTime": -1.0,
      "FadeOutTime": -1.0,
      "Segments": [
        0,
        0,
        0,
        0.5,
        -4,
        0,
        2.167,
        4,
        1,
        2.945,
        4,
        3.722,
        2.103,
        4.5,
        -2,
        1,
        5.111,
        -5.224,
        5.722,
        -7,
        6.333,
        -7,
        1,
        6.422,
        -7,
        6.511,
        -2.953,
        6.6,
        0,
        1,
        6.767,
        5.537,
        6.933,
        7,
        7.1,
        7,
        0,
        7.6,
        0,
        0,
        8.333,
        2,
        0,
        9.833,
        -2,
        0,
        10.5,
        0
      ]
    },
    {
      "Target": "Parameter",
      "Id": "Param56",
      "FadeInTime": -1.0,
      "FadeOutTime": -1.0,
      "Segments": [
        0,
        0,
        0,
        1,
        -15,
        0,
        3.333,
        15,
        0,
        5.667,
        15,
        0,
        6.7,
        -15,
        0,
        7.2,
        15,
        0,
        7.867,
        -15,
        0,
        9.033,
        15,
        0,
        10.5,
        0
      ]
    },
    {
      "Target": "Parameter",
      "Id": "Param57",
      "FadeInTime": -1.0,
      "FadeOutTime": -1.0,
      "Segments": [
        0,
        0,
        0,
        0.5,
        -30,
        0,
        2.167,
        30,
        0,
        4.5,
        -30,
        1,
        5.178,
        -30,
        5.855,
        -27.165,
        6.533,
        -16,
        1,
        6.7,
        -13.254,
        6.866,
        16,
        7.033,
        16,
        0,
        7.533,
        -16,
        0,
        8.2,
        16,
        0,
        9.7,
        -18,
        0,
        10.5,
        0
      ]
    },
    {
      "Target": "Parameter",
      "Id": "Param92",
      "FadeInTime": -1.0,
      "FadeOutTime": -1.0,
      "Segments": [
        0,
        0,
        0,
        1,
        0,
        0,
        3.333,
        0,
        0,
        6.333,
        0,
        0,
        6.833,
        0,
        0,
        7.333,
        0,
        0,
        8,
        0,
        0,
        9.167,
        0,
        0,
        10.5,
        0
      ]
    },
    {
      "Target": "Parameter",
      "Id": "Param95",
      "FadeInTime": -1.0,
      "FadeOutTime": -1.0,
      "Segments": [
        0,
        0,
        0,
        1,
        0,
        0,
        3.333,
        0,
        0,
        6.333,
        0,
        0,
        6.833,
        0,
        0,
        7.333,
        0,
        0,
        8,
        0,
        0,
        9.167,
        0,
        0,
        10.5,
        0
      ]
    },
    {
      "Target": "Parameter",
      "Id": "Param100",
      "FadeInTime": -1.0,
      "FadeOutTime": -1.0,
      "Segments": [
        0,
        0,
        0,
        10.5,
        0
      ]
    },
    {
      "Target": "Parameter",
      "Id": "Param112",
      "FadeInTime": -1.0,
      "FadeOutTime": -1.0,
      "Segments": [
        0,
        0,
        0,
        10.5,
        0
      ]
    },
    {
      "Target": "Parameter",
      "Id": "Param101",
      "FadeInTime": -1.0,
      "FadeOutTime": -1.0,
      "Segments": [
        0,
        0,
        0,
        10.5,
        0
      ]
    },
    {
      "Target": "Parameter",
      "Id": "Param102",
      "FadeInTime": -1.0,
      "FadeOutTime": -1.0,
      "Segments": [
        0,
        0,
        0,
        10.5,
        0
      ]
    },
    {
      "Target": "Parameter",
      "Id": "Param103",
      "FadeInTime": -1.0,
      "FadeOutTime": -1.0,
      "Segments": [
        0,
        0,
        0,
        10.5,
        0
      ]
    },
    {
      "Target": "Parameter",
      "Id": "Param104",
      "FadeInTime": -1.0,
      "FadeOutTime": -1.0,
      "Segments": [
        0,
        0,
        0,
        10.5,
        0
      ]
    },
    {
      "Target": "Parameter",
      "Id": "Param105",
      "FadeInTime": -1.0,
      "FadeOutTime": -1.0,
      "Segments": [
        0,
        0,
        0,
        10.5,
        0
      ]
    },
    {
      "Target": "Parameter",
      "Id": "Param46",
      "FadeInTime": -1.0,
      "FadeOutTime": -1.0,
      "Segments": [
        0,
        0,
        0,
        0.333,
        0,
        0,
        1,
        0,
        0,
        3.333,
        0,
        0,
        6.333,
        0,
        0,
        6.833,
        0,
        0,
        7.333,
        0,
        0,
        8,
        0,
        0,
        9.167,
        0,
        0,
        10.5,
        0
      ]
    },
    {
      "Target": "Parameter",
      "Id": "Param60",
      "FadeInTime": -1.0,
      "FadeOutTime": -1.0,
      "Segments": [
        0,
        0,
        0,
        0.333,
        0,
        0,
        1,
        0,
        0,
        3.333,
        0,
        1,
        4.333,
        0,
        5.333,
        0.715,
        6.333,
        3,
        1,
        6.5,
        3.381,
        6.666,
        7,
        6.833,
        7,
        0,
        7.333,
        2.1,
        1,
        7.555,
        2.1,
        7.778,
        3.726,
        8,
        4.167,
        1,
        8.389,
        4.938,
        8.778,
        5,
        9.167,
        5,
        0,
        10.5,
        0
      ]
    },
    {
      "Target": "Parameter",
      "Id": "Param61",
      "FadeInTime": -1.0,
      "FadeOutTime": -1.0,
      "Segments": [
        0,
        0,
        0,
        0.333,
        0,
        0,
        1,
        0,
        0,
        3.333,
        0,
        1,
        4.333,
        0,
        5.333,
        -0.473,
        6.333,
        -2,
        1,
        6.5,
        -2.254,
        6.666,
        -5,
        6.833,
        -5,
        0,
        7.333,
        -1.38,
        1,
        7.555,
        -1.38,
        7.778,
        -2.458,
        8,
        -2.907,
        1,
        8.389,
        -3.692,
        8.778,
        -3.8,
        9.167,
        -3.8,
        0,
        10.5,
        0
      ]
    },
    {
      "Target": "Parameter",
      "Id": "Param62",
      "FadeInTime": -1.0,
      "FadeOutTime": -1.0,
      "Segments": [
        0,
        0,
        0,
        0.667,
        -7,
        0,
        2.167,
        0,
        1,
        2.556,
        0,
        2.944,
        -7.341,
        3.333,
        -9,
        1,
        4.333,
        -13.267,
        5.333,
        -14,
        6.333,
        -14,
        1,
        6.5,
        -14,
        6.666,
        -4.16,
        6.833,
        -3,
        1,
        7.222,
        -0.294,
        7.611,
        0,
        8,
        0,
        0,
        9.167,
        0,
        0,
        10.5,
        0
      ]
    },
    {
      "Target": "Parameter",
      "Id": "Param63",
      "FadeInTime": -1.0,
      "FadeOutTime": -1.0,
      "Segments": [
        0,
        0,
        0,
        0.333,
        6,
        0,
        1,
        -5,
        1,
        1.778,
        -5,
        2.555,
        0.611,
        3.333,
        9,
        1,
        4.333,
        19.786,
        5.333,
        24,
        6.333,
        24,
        0,
        6.833,
        0,
        0,
        7.333,
        14,
        0,
        8,
        0,
        0,
        9.167,
        14,
        0,
        10.5,
        0
      ]
    },
    {
      "Target": "Parameter",
      "Id": "Param106",
      "FadeInTime": -1.0,
      "FadeOutTime": -1.0,
      "Segments": [
        0,
        0,
        0,
        10.5,
        0
      ]
    },
    {
      "Target": "Parameter",
      "Id": "Param113",
      "FadeInTime": -1.0,
      "FadeOutTime": -1.0,
      "Segments": [
        0,
        0,
        0,
        10.5,
        0
      ]
    },
    {
      "Target": "Parameter",
      "Id": "Param115",
      "FadeInTime": -1.0,
      "FadeOutTime": -1.0,
      "Segments": [
        0,
        0,
        0,
        10.5,
        0
      ]
    },
    {
      "Target": "Parameter",
      "Id": "Param114",
      "FadeInTime": -1.0,
      "FadeOutTime": -1.0,
      "Segments": [
        0,
        0,
        0,
        10.5,
        0
      ]
    },
    {
      "Target": "Parameter",
      "Id": "Param107",
      "FadeInTime": -1.0,
      "FadeOutTime": -1.0,
      "Segments": [
        0,
        0,
        0,
        10.5,
        0
      ]
    },
    {
      "Target": "Parameter",
      "Id": "Param108",
      "FadeInTime": -1.0,
      "FadeOutTime": -1.0,
      "Segments": [
        0,
        0,
        0,
        10.5,
        0
      ]
    },
    {
      "Target": "Parameter",
      "Id": "Param109",
      "FadeInTime": -1.0,
      "FadeOutTime": -1.0,
      "Segments": [
        0,
        0,
        0,
        10.5,
        0
      ]
    },
    {
      "Target": "Parameter",
      "Id": "Param110",
      "FadeInTime": -1.0,
      "FadeOutTime": -1.0,
      "Segments": [
        0,
        0,
        0,
        10.5,
        0
      ]
    },
    {
      "Target": "Parameter",
      "Id": "Param111",
      "FadeInTime": -1.0,
      "FadeOutTime": -1.0,
      "Segments": [
        0,
        0,
        0,
        10.5,
        0
      ]
    },
    {
      "Target": "Parameter",
      "Id": "Param99",
      "FadeInTime": -1.0,
      "FadeOutTime": -1.0,
      "Segments": [
        0,
        0,
        0,
        10.5,
        0
      ]
    },
    {
      "Target": "Parameter",
      "Id": "Param47",
      "FadeInTime": -1.0,
      "FadeOutTime": -1.0,
      "Segments": [
        0,
        0,
        0,
        0.333,
        0,
        0,
        1,
        0,
        0,
        3.333,
        0,
        0,
        6.333,
        0,
        0,
        6.833,
        0,
        0,
        7.333,
        0,
        0,
        8,
        0,
        0,
        9.167,
        0,
        0,
        10.5,
        0
      ]
    },
    {
      "Target": "Parameter",
      "Id": "Param93",
      "FadeInTime": -1.0,
      "FadeOutTime": -1.0,
      "Segments": [
        0,
        0,
        0,
        0.333,
        0,
        0,
        1,
        0,
        0,
        3.333,
        0,
        0,
        6.333,
        0,
        0,
        6.833,
        0,
        0,
        7.333,
        0,
        0,
        8,
        0,
        0,
        9.167,
        0,
        0,
        10.5,
        0
      ]
    },
    {
      "Target": "Parameter",
      "Id": "Param74",
      "FadeInTime": -1.0,
      "FadeOutTime": -1.0,
      "Segments": [
        0,
        0,
        0,
        0.333,
        4,
        1,
        0.555,
        4,
        0.778,
        3.287,
        1,
        1.125,
        1,
        1.389,
        -2.659,
        1.778,
        -5,
        2.167,
        -5,
        1,
        2.556,
        -5,
        2.944,
        -3.008,
        3.333,
        0,
        1,
        3.555,
        1.719,
        3.778,
        4.298,
        4,
        4.404,
        1,
        4.778,
        4.773,
        5.555,
        4.926,
        6.333,
        5.28,
        1,
        6.5,
        5.356,
        6.666,
        13,
        6.833,
        13,
        0,
        7.333,
        5,
        1,
        7.555,
        5,
        7.778,
        7.535,
        8,
        8.375,
        1,
        8.389,
        9.845,
        8.778,
        10,
        9.167,
        10,
        0,
        10.5,
        0
      ]
    },
    {
      "Target": "Parameter",
      "Id": "Param65",
      "FadeInTime": -1.0,
      "FadeOutTime": -1.0,
      "Segments": [
        0,
        0,
        0,
        0.667,
        -15,
        1,
        0.945,
        -15,
        1.222,
        -4.652,
        1.5,
        -1.687,
        1,
        2.444,
        8.394,
        3.389,
        11,
        4.333,
        11,
        1,
        5.055,
        11,
        5.778,
        -1.707,
        6.5,
        -17,
        1,
        6.667,
        -20.529,
        6.833,
        -20,
        7,
        -20,
        0,
        7.5,
        -8,
        0,
        8.167,
        -19,
        1,
        8.556,
        -19,
        8.944,
        -18.984,
        9.333,
        -14.262,
        1,
        9.722,
        -9.54,
        10.111,
        0,
        10.5,
        0
      ]
    },
    {
      "Target": "Parameter",
      "Id": "Param66",
      "FadeInTime": -1.0,
      "FadeOutTime": -1.0,
      "Segments": [
        0,
        0,
        0,
        0.333,
        14,
        0,
        2.5,
        4,
        0,
        5.5,
        20,
        1,
        5.9,
        20,
        6.3,
        14.204,
        6.7,
        0,
        1,
        6.856,
        -5.524,
        7.011,
        -10,
        7.167,
        -10,
        0,
        7.667,
        20,
        0,
        8.333,
        0,
        0,
        9.5,
        20,
        0,
        10.5,
        0
      ]
    },
    {
      "Target": "Parameter",
      "Id": "Param67",
      "FadeInTime": -1.0,
      "FadeOutTime": -1.0,
      "Segments": [
        0,
        0,
        0,
        0.333,
        0,
        0,
        1,
        0,
        0,
        3.333,
        0,
        0,
        6.333,
        0,
        0,
        6.833,
        0,
        0,
        7.333,
        0,
        0,
        8,
        0,
        0,
        9.167,
        0,
        0,
        10.5,
        0
      ]
    },
    {
      "Target": "Parameter",
      "Id": "Param64",
      "FadeInTime": -1.0,
      "FadeOutTime": -1.0,
      "Segments": [
        0,
        0,
        0,
        0.333,
        0,
        0,
        1,
        0,
        0,
        3.333,
        0,
        0,
        6.333,
        0,
        0,
        6.833,
        0,
        0,
        7.333,
        0,
        0,
        8,
        0,
        0,
        9.167,
        0,
        0,
        10.5,
        0
      ]
    },
    {
      "Target": "Parameter",
      "Id": "Param161",
      "FadeInTime": -1.0,
      "FadeOutTime": -1.0,
      "Segments": [
        0,
        0,
        0,
        10.5,
        0
      ]
    },
    {
      "Target": "Parameter",
      "Id": "Param159",
      "FadeInTime": -1.0,
      "FadeOutTime": -1.0,
      "Segments": [
        0,
        0,
        0,
        0.667,
        -30,
        0,
        2.167,
        -30,
        0,
        4.333,
        0,
        0,
        6.333,
        0,
        0,
        6.833,
        -30,
        0,
        9.167,
        -30,
        0,
        10.5,
        0
      ]
    },
    {
      "Target": "Parameter",
      "Id": "Param48",
      "FadeInTime": -1.0,
      "FadeOutTime": -1.0,
      "Segments": [
        0,
        0,
        0,
        1,
        0,
        0,
        3.333,
        0,
        0,
        6.333,
        0,
        0,
        6.833,
        0,
        0,
        7.333,
        0,
        0,
        8,
        0,
        0,
        9.167,
        0,
        0,
        10.5,
        0
      ]
    },
    {
      "Target": "Parameter",
      "Id": "Param94",
      "FadeInTime": -1.0,
      "FadeOutTime": -1.0,
      "Segments": [
        0,
        0,
        0,
        1,
        0,
        0,
        3.333,
        0,
        0,
        6.333,
        0,
        0,
        6.833,
        0,
        0,
        7.333,
        0,
        0,
        8,
        0,
        0,
        9.167,
        0,
        0,
        10.5,
        0
      ]
    },
    {
      "Target": "Parameter",
      "Id": "Param75",
      "FadeInTime": -1.0,
      "FadeOutTime": -1.0,
      "Segments": [
        0,
        0,
        1,
        0.333,
        0,
        0.667,
        11.361,
        1,
        12,
        1,
        1.333,
        12.639,
        1.667,
        12.5,
        2,
        12.5,
        0,
        3.333,
        11.02,
        0,
        4.833,
        12,
        0,
        6.333,
        -1.42,
        0,
        6.833,
        13,
        0,
        7.333,
        6,
        0,
        8,
        8.113,
        1,
        8.389,
        8.113,
        8.778,
        8.315,
        9.167,
        7,
        1,
        9.611,
        5.497,
        10.056,
        0,
        10.5,
        0
      ]
    },
    {
      "Target": "Parameter",
      "Id": "Param69",
      "FadeInTime": -1.0,
      "FadeOutTime": -1.0,
      "Segments": [
        0,
        0,
        0,
        0.5,
        -15,
        0,
        2,
        -7.5,
        1,
        2.389,
        -7.5,
        2.778,
        -12.44,
        3.167,
        -22.5,
        1,
        3.222,
        -23.937,
        3.278,
        -26.491,
        3.333,
        -27,
        1,
        3.583,
        -29.289,
        3.833,
        -30,
        4.083,
        -30,
        1,
        4.333,
        -30,
        4.583,
        -30,
        4.833,
        -28,
        1,
        5.333,
        -21.405,
        5.833,
        16,
        6.333,
        16,
        0,
        6.667,
        -30,
        0,
        7.167,
        -15,
        1,
        7.334,
        -15,
        7.5,
        -23.778,
        7.667,
        -25.375,
        1,
        8,
        -28.569,
        8.334,
        -28.86,
        8.667,
        -28.86,
        0,
        10.5,
        0
      ]
    },
    {
      "Target": "Parameter",
      "Id": "Param70",
      "FadeInTime": -1.0,
      "FadeOutTime": -1.0,
      "Segments": [
        0,
        0,
        0,
        0.25,
        14,
        0,
        1,
        -8,
        0,
        3.333,
        13,
        1,
        3.583,
        13,
        3.833,
        11.565,
        4.083,
        9,
        1,
        4.222,
        7.575,
        4.361,
        6.9,
        4.5,
        5,
        1,
        4.611,
        3.48,
        4.722,
        0,
        4.833,
        0,
        0,
        6.333,
        0,
        0,
        6.533,
        9,
        0,
        6.933,
        -8,
        0,
        7.333,
        12,
        0,
        9.167,
        -5,
        0,
        10.5,
        0
      ]
    },
    {
      "Target": "Parameter",
      "Id": "Param71",
      "FadeInTime": -1.0,
      "FadeOutTime": -1.0,
      "Segments": [
        0,
        0,
        0,
        0.533,
        30,
        0,
        2,
        -30,
        0,
        3.333,
        30,
        0,
        4.083,
        30,
        0,
        4.833,
        30,
        0,
        5.633,
        -30,
        1,
        5.866,
        -30,
        6.1,
        -23.715,
        6.333,
        0,
        1,
        6.444,
        11.293,
        6.556,
        30,
        6.667,
        30,
        0,
        7.167,
        -30,
        0,
        7.667,
        30,
        0,
        8.667,
        -8,
        0,
        9.833,
        30,
        0,
        10.5,
        0
      ]
    },
    {
      "Target": "Parameter",
      "Id": "Param68",
      "FadeInTime": -1.0,
      "FadeOutTime": -1.0,
      "Segments": [
        0,
        0,
        0,
        0.533,
        27,
        0,
        1,
        0,
        0,
        3.333,
        15,
        0,
        6.333,
        -15,
        0,
        6.833,
        0,
        0,
        7.333,
        -15,
        1,
        7.555,
        -15,
        7.778,
        -4.877,
        8,
        0,
        1,
        8.389,
        8.535,
        8.778,
        10,
        9.167,
        10,
        0,
        10.5,
        0
      ]
    },
    {
      "Target": "Parameter",
      "Id": "Param160",
      "FadeInTime": -1.0,
      "FadeOutTime": -1.0,
      "Segments": [
        0,
        0,
        0,
        10.5,
        0
      ]
    },
    {
      "Target": "Parameter",
      "Id": "Param162",
      "FadeInTime": -1.0,
      "FadeOutTime": -1.0,
      "Segments": [
        0,
        0,
        0,
        10.5,
        0
      ]
    },
    {
      "Target": "Parameter",
      "Id": "Param158",
      "FadeInTime": -1.0,
      "FadeOutTime": -1.0,
      "Segments": [
        0,
        0,
        0,
        1,
        30,
        0,
        2,
        30,
        0,
        5.633,
        30,
        0,
        6.333,
        0,
        0,
        6.833,
        30,
        0,
        7.333,
        0,
        0,
        8,
        30,
        0,
        9.167,
        30,
        0,
        10.5,
        0
      ]
    },
    {
      "Target": "Parameter",
      "Id": "Param10",
      "FadeInTime": -1.0,
      "FadeOutTime": -1.0,
      "Segments": [
        0,
        0,
        0,
        1,
        9,
        0,
        2.167,
        -9,
        0,
        4.5,
        9,
        0,
        6.333,
        -9,
        0,
        7,
        9,
        0,
        7.667,
        -9,
        0,
        8.5,
        9,
        0,
        9.667,
        -9,
        0,
        10.5,
        0
      ]
    },
    {
      "Target": "Parameter",
      "Id": "Param11",
      "FadeInTime": -1.0,
      "FadeOutTime": -1.0,
      "Segments": [
        0,
        0,
        0,
        0.333,
        -4,
        0,
        1.167,
        11,
        0,
        2.333,
        -11,
        0,
        4.667,
        11,
        0,
        6.5,
        -11,
        0,
        7.167,
        11,
        0,
        7.833,
        -11,
        0,
        8.667,
        11,
        0,
        9.833,
        -11,
        0,
        10.5,
        0
      ]
    },
    {
      "Target": "Parameter",
      "Id": "Param12",
      "FadeInTime": -1.0,
      "FadeOutTime": -1.0,
      "Segments": [
        0,
        0,
        0,
        0.5,
        -7,
        0,
        1.333,
        15,
        0,
        2.5,
        -15,
        0,
        4.833,
        15,
        0,
        6.667,
        -15,
        0,
        7.333,
        15,
        0,
        8,
        -15,
        0,
        8.833,
        15,
        0,
        10,
        -15,
        0,
        10.5,
        0
      ]
    },
    {
      "Target": "Parameter",
      "Id": "Param13",
      "FadeInTime": -1.0,
      "FadeOutTime": -1.0,
      "Segments": [
        0,
        0,
        0,
        0.667,
        -10,
        0,
        1.5,
        19,
        0,
        2.667,
        -19,
        0,
        5,
        19,
        0,
        6.833,
        -19,
        0,
        7.5,
        19,
        0,
        8.167,
        -19,
        0,
        9,
        19,
        0,
        10.167,
        -19,
        0,
        10.5,
        0
      ]
    },
    {
      "Target": "Parameter",
      "Id": "Param14",
      "FadeInTime": -1.0,
      "FadeOutTime": -1.0,
      "Segments": [
        0,
        0,
        0,
        0.833,
        -12,
        0,
        1.667,
        25,
        0,
        2.833,
        -25,
        0,
        5.167,
        25,
        0,
        7,
        -25,
        0,
        7.667,
        25,
        0,
        8.333,
        -25,
        0,
        9.167,
        25,
        0,
        10.333,
        -25,
        0,
        10.5,
        0
      ]
    },
    {
      "Target": "Parameter",
      "Id": "Param3",
      "FadeInTime": -1.0,
      "FadeOutTime": -1.0,
      "Segments": [
        0,
        0,
        0,
        1.167,
        5,
        0,
        2.333,
        -5,
        0,
        4.667,
        5,
        0,
        6.5,
        -5,
        0,
        7.167,
        5,
        0,
        7.833,
        -5,
        0,
        8.667,
        5,
        0,
        9.833,
        -5,
        0,
        10.5,
        0
      ]
    },
    {
      "Target": "Parameter",
      "Id": "Param4",
      "FadeInTime": -1.0,
      "FadeOutTime": -1.0,
      "Segments": [
        0,
        0,
        0,
        0.5,
        -5,
        0,
        1.333,
        10,
        0,
        2.5,
        -10,
        0,
        4.833,
        10,
        0,
        6.667,
        -10,
        0,
        7.333,
        10,
        0,
        8,
        -10,
        0,
        8.833,
        10,
        0,
        10,
        -10,
        0,
        10.5,
        0
      ]
    },
    {
      "Target": "Parameter",
      "Id": "Param5",
      "FadeInTime": -1.0,
      "FadeOutTime": -1.0,
      "Segments": [
        0,
        0,
        0,
        0.667,
        -8,
        0,
        1.5,
        15,
        0,
        2.667,
        -15,
        0,
        5,
        15,
        0,
        6.833,
        -15,
        0,
        7.5,
        15,
        0,
        8.167,
        -15,
        0,
        9,
        15,
        0,
        10.167,
        -15,
        0,
        10.5,
        0
      ]
    },
    {
      "Target": "Parameter",
      "Id": "Param9",
      "FadeInTime": -1.0,
      "FadeOutTime": -1.0,
      "Segments": [
        0,
        0,
        0,
        0.833,
        -12,
        0,
        1.667,
        19,
        0,
        2.833,
        -19,
        0,
        5.167,
        19,
        0,
        7,
        -19,
        0,
        7.667,
        19,
        0,
        8.333,
        -19,
        0,
        9.167,
        19,
        0,
        10.333,
        -19,
        0,
        10.5,
        0
      ]
    },
    {
      "Target": "Parameter",
      "Id": "Param6",
      "FadeInTime": -1.0,
      "FadeOutTime": -1.0,
      "Segments": [
        0,
        0,
        0,
        0.667,
        -3,
        0,
        1.5,
        6,
        0,
        2.667,
        -6,
        0,
        5,
        6,
        0,
        6.833,
        -6,
        0,
        7.5,
        6,
        0,
        8.167,
        -6,
        0,
        9,
        6,
        0,
        10.167,
        -6,
        0,
        10.5,
        0
      ]
    },
    {
      "Target": "Parameter",
      "Id": "Param8",
      "FadeInTime": -1.0,
      "FadeOutTime": -1.0,
      "Segments": [
        0,
        0,
        0,
        0.333,
        6,
        0,
        0.833,
        -4,
        0,
        1.667,
        13,
        0,
        2.833,
        -13,
        0,
        5.167,
        13,
        0,
        7,
        -13,
        0,
        7.667,
        13,
        0,
        8.333,
        -13,
        0,
        9.167,
        13,
        0,
        10.333,
        -13,
        0,
        10.5,
        0
      ]
    },
    {
      "Target": "Parameter",
      "Id": "Param7",
      "FadeInTime": -1.0,
      "FadeOutTime": -1.0,
      "Segments": [
        0,
        0,
        0,
        0.5,
        9,
        0,
        1,
        -9,
        0,
        1.833,
        20,
        0,
        3,
        -20,
        0,
        5.333,
        20,
        0,
        7.167,
        -20,
        0,
        7.833,
        20,
        0,
        8.5,
        -20,
        0,
        9.333,
        20,
        0,
        10.5,
        0
      ]
    },
    {
      "Target": "Parameter",
      "Id": "Param15",
      "FadeInTime": -1.0,
      "FadeOutTime": -1.0,
      "Segments": [
        0,
        0,
        0,
        1.5,
        5,
        0,
        2.667,
        -5,
        0,
        5,
        5,
        0,
        6.833,
        -5,
        0,
        7.5,
        5,
        0,
        8.167,
        -5,
        0,
        9,
        5,
        0,
        10.167,
        -5,
        0,
        10.5,
        0
      ]
    },
    {
      "Target": "Parameter",
      "Id": "Param16",
      "FadeInTime": -1.0,
      "FadeOutTime": -1.0,
      "Segments": [
        0,
        0,
        0,
        0.333,
        12,
        0,
        0.833,
        -6,
        0,
        1.667,
        12,
        0,
        2.833,
        -12,
        0,
        5.167,
        12,
        0,
        7,
        -12,
        0,
        7.667,
        12,
        0,
        8.333,
        -12,
        0,
        9.167,
        12,
        0,
        10.333,
        -12,
        0,
        10.5,
        0
      ]
    },
    {
      "Target": "Parameter",
      "Id": "Param17",
      "FadeInTime": -1.0,
      "FadeOutTime": -1.0,
      "Segments": [
        0,
        0,
        0,
        0.5,
        18,
        0,
        1,
        -10,
        0,
        1.833,
        18,
        0,
        3,
        -18,
        0,
        5.333,
        18,
        0,
        7.167,
        -18,
        0,
        7.833,
        18,
        0,
        8.5,
        -18,
        0,
        9.333,
        18,
        0,
        10.5,
        0
      ]
    },
    {
      "Target": "Parameter",
      "Id": "Param18",
      "FadeInTime": -1.0,
      "FadeOutTime": -1.0,
      "Segments": [
        0,
        0,
        0,
        0.667,
        24,
        0,
        1.133,
        -15,
        0,
        2,
        24,
        0,
        3.167,
        -24,
        0,
        5.5,
        24,
        0,
        7.333,
        -24,
        0,
        8,
        24,
        0,
        8.667,
        -24,
        0,
        9.5,
        24,
        0,
        10.5,
        0
      ]
    },
    {
      "Target": "Parameter",
      "Id": "Param19",
      "FadeInTime": -1.0,
      "FadeOutTime": -1.0,
      "Segments": [
        0,
        0,
        0,
        1.333,
        -19,
        0,
        2.167,
        30,
        0,
        3.333,
        -30,
        0,
        5.667,
        30,
        0,
        7.5,
        -30,
        0,
        8.167,
        30,
        0,
        8.833,
        -30,
        0,
        9.667,
        30,
        0,
        10.5,
        0
      ]
    },
    {
      "Target": "Parameter",
      "Id": "Param20",
      "FadeInTime": -1.0,
      "FadeOutTime": -1.0,
      "Segments": [
        0,
        0,
        0,
        0.833,
        -6,
        0,
        1.667,
        6,
        0,
        2.833,
        -6,
        0,
        5.167,
        6,
        0,
        7,
        -6,
        0,
        7.667,
        6,
        0,
        8.333,
        -6,
        0,
        9.167,
        6,
        0,
        10.333,
        -6,
        0,
        10.5,
        0
      ]
    },
    {
      "Target": "Parameter",
      "Id": "Param21",
      "FadeInTime": -1.0,
      "FadeOutTime": -1.0,
      "Segments": [
        0,
        0,
        0,
        0.333,
        10,
        0,
        1,
        -9,
        0,
        1.833,
        10,
        0,
        3,
        -10,
        0,
        5.333,
        10,
        0,
        7.167,
        -10,
        0,
        7.833,
        10,
        0,
        8.5,
        -10,
        0,
        9.333,
        10,
        0,
        10.5,
        0
      ]
    },
    {
      "Target": "Parameter",
      "Id": "Param22",
      "FadeInTime": -1.0,
      "FadeOutTime": -1.0,
      "Segments": [
        0,
        0,
        0,
        0.5,
        17,
        0,
        1.167,
        -13,
        0,
        2,
        17,
        0,
        3.167,
        -17,
        0,
        5.5,
        17,
        0,
        7.333,
        -17,
        0,
        8,
        17,
        0,
        8.667,
        -17,
        0,
        9.5,
        17,
        0,
        10.5,
        0
      ]
    },
    {
      "Target": "Parameter",
      "Id": "Param23",
      "FadeInTime": -1.0,
      "FadeOutTime": -1.0,
      "Segments": [
        0,
        0,
        0,
        0.667,
        23,
        0,
        1.333,
        -17,
        0,
        2.167,
        23,
        0,
        3.333,
        -23,
        0,
        5.667,
        23,
        0,
        7.5,
        -23,
        0,
        8.167,
        23,
        0,
        8.833,
        -23,
        0,
        9.667,
        23,
        0,
        10.5,
        0
      ]
    },
    {
      "Target": "Parameter",
      "Id": "Param24",
      "FadeInTime": -1.0,
      "FadeOutTime": -1.0,
      "Segments": [
        0,
        0,
        0,
        1.5,
        -21,
        0,
        2.333,
        30,
        0,
        3.5,
        -30,
        0,
        5.833,
        30,
        0,
        7.667,
        -30,
        0,
        8.333,
        30,
        0,
        9,
        -30,
        0,
        9.833,
        30,
        0,
        10.5,
        0
      ]
    },
    {
      "Target": "Parameter",
      "Id": "Param25",
      "FadeInTime": -1.0,
      "FadeOutTime": -1.0,
      "Segments": [
        0,
        0,
        0,
        1,
        -5,
        0,
        1.833,
        5,
        0,
        3,
        -5,
        0,
        5.333,
        5,
        0,
        7.167,
        -5,
        0,
        7.833,
        5,
        0,
        8.5,
        -5,
        0,
        9.333,
        5,
        0,
        10.5,
        0
      ]
    },
    {
      "Target": "Parameter",
      "Id": "Param26",
      "FadeInTime": -1.0,
      "FadeOutTime": -1.0,
      "Segments": [
        0,
        0,
        0,
        0.5,
        10,
        0,
        1.167,
        -9,
        0,
        2,
        10,
        0,
        3.167,
        -10,
        0,
        5.5,
        10,
        0,
        7.333,
        -10,
        0,
        8,
        10,
        0,
        8.667,
        -10,
        0,
        9.5,
        10,
        0,
        10.5,
        0
      ]
    },
    {
      "Target": "Parameter",
      "Id": "Param27",
      "FadeInTime": -1.0,
      "FadeOutTime": -1.0,
      "Segments": [
        0,
        0,
        0,
        0.667,
        15,
        0,
        1.333,
        -14,
        0,
        2.167,
        15,
        0,
        3.333,
        -15,
        0,
        5.667,
        15,
        0,
        7.5,
        -15,
        0,
        8.167,
        15,
        0,
        8.833,
        -15,
        0,
        9.667,
        15,
        0,
        10.5,
        0
      ]
    },
    {
      "Target": "Parameter",
      "Id": "Param28",
      "FadeInTime": -1.0,
      "FadeOutTime": -1.0,
      "Segments": [
        0,
        0,
        0,
        0.833,
        22,
        0,
        1.5,
        -19,
        0,
        2.333,
        22,
        0,
        3.5,
        -22,
        0,
        5.833,
        22,
        0,
        7.667,
        -22,
        0,
        8.333,
        22,
        0,
        9,
        -22,
        0,
        9.833,
        22,
        0,
        10.5,
        0
      ]
    },
    {
      "Target": "Parameter",
      "Id": "Param29",
      "FadeInTime": -1.0,
      "FadeOutTime": -1.0,
      "Segments": [
        0,
        0,
        0,
        1,
        27,
        0,
        1.667,
        -23,
        0,
        2.5,
        27,
        0,
        3.667,
        -27,
        0,
        6,
        27,
        0,
        7.833,
        -27,
        0,
        8.5,
        27,
        0,
        9.167,
        -27,
        0,
        10,
        27,
        0,
        10.5,
        0
      ]
    },
    {
      "Target": "Parameter",
      "Id": "Param30",
      "FadeInTime": -1.0,
      "FadeOutTime": -1.0,
      "Segments": [
        0,
        0,
        0,
        1.167,
        -3,
        0,
        2,
        3,
        0,
        3.167,
        -3,
        0,
        5.5,
        3,
        0,
        7.333,
        -3,
        0,
        8,
        3,
        0,
        8.667,
        -3,
        0,
        9.5,
        3,
        0,
        10.5,
        0
      ]
    },
    {
      "Target": "Parameter",
      "Id": "Param31",
      "FadeInTime": -1.0,
      "FadeOutTime": -1.0,
      "Segments": [
        0,
        0,
        0,
        0.5,
        8,
        0,
        1.333,
        -6,
        0,
        2.167,
        8,
        0,
        3.333,
        -8,
        0,
        5.667,
        8,
        0,
        7.5,
        -8,
        0,
        8.167,
        8,
        0,
        8.833,
        -8,
        0,
        9.667,
        8,
        0,
        10.5,
        0
      ]
    },
    {
      "Target": "Parameter",
      "Id": "Param32",
      "FadeInTime": -1.0,
      "FadeOutTime": -1.0,
      "Segments": [
        0,
        0,
        0,
        0.667,
        13,
        0,
        1.5,
        -11,
        0,
        2.333,
        13,
        0,
        3.5,
        -13,
        0,
        5.833,
        13,
        0,
        7.667,
        -13,
        0,
        8.333,
        13,
        0,
        9,
        -13,
        0,
        9.833,
        13,
        0,
        10.5,
        0
      ]
    },
    {
      "Target": "Parameter",
      "Id": "Param33",
      "FadeInTime": -1.0,
      "FadeOutTime": -1.0,
      "Segments": [
        0,
        0,
        0,
        0.833,
        18,
        0,
        1.667,
        -17,
        0,
        2.5,
        18,
        0,
        3.667,
        -18,
        0,
        6,
        18,
        0,
        7.833,
        -18,
        0,
        8.5,
        18,
        0,
        9.167,
        -18,
        0,
        10,
        18,
        0,
        10.5,
        0
      ]
    },
    {
      "Target": "Parameter",
      "Id": "Param34",
      "FadeInTime": -1.0,
      "FadeOutTime": -1.0,
      "Segments": [
        0,
        0,
        0,
        1,
        25,
        0,
        1.833,
        -22,
        0,
        2.667,
        25,
        0,
        3.833,
        -25,
        0,
        6.167,
        25,
        0,
        8,
        -25,
        0,
        8.667,
        25,
        0,
        9.333,
        -25,
        0,
        10.167,
        25,
        0,
        10.5,
        0
      ]
    },
    {
      "Target": "Parameter",
      "Id": "Param137",
      "FadeInTime": -1.0,
      "FadeOutTime": -1.0,
      "Segments": [
        0,
        0,
        0,
        1,
        -13,
        0,
        1.833,
        0,
        0,
        2.667,
        -18,
        0,
        3.833,
        0,
        0,
        5.133,
        -30,
        1,
        5.478,
        -30,
        5.822,
        -25.161,
        6.167,
        -18,
        1,
        6.778,
        -5.295,
        7.389,
        0,
        8,
        0,
        0,
        8.667,
        -18,
        0,
        9.333,
        0,
        0,
        10.167,
        -18,
        0,
        10.5,
        0
      ]
    },
    {
      "Target": "Parameter",
      "Id": "Param35",
      "FadeInTime": -1.0,
      "FadeOutTime": -1.0,
      "Segments": [
        0,
        0,
        0,
        0.667,
        9,
        0,
        2.7,
        -9,
        0,
        4,
        9,
        0,
        5.333,
        -9,
        0,
        6.333,
        9,
        0,
        6.833,
        -9,
        0,
        7.333,
        9,
        0,
        8,
        -9,
        0,
        9.167,
        9,
        0,
        10.5,
        0
      ]
    },
    {
      "Target": "Parameter",
      "Id": "Param36",
      "FadeInTime": -1.0,
      "FadeOutTime": -1.0,
      "Segments": [
        0,
        0,
        0,
        1,
        10,
        0,
        3.033,
        -10,
        0,
        4.333,
        10,
        0,
        5.667,
        -10,
        0,
        6.667,
        10,
        0,
        7.167,
        -10,
        0,
        7.667,
        10,
        0,
        8.333,
        -10,
        0,
        9.5,
        10,
        0,
        10.5,
        0
      ]
    },
    {
      "Target": "Parameter",
      "Id": "Param37",
      "FadeInTime": -1.0,
      "FadeOutTime": -1.0,
      "Segments": [
        0,
        0,
        0,
        1.333,
        15,
        0,
        3.367,
        -15,
        0,
        4.667,
        15,
        0,
        6,
        -15,
        0,
        7,
        15,
        0,
        7.5,
        -15,
        0,
        8,
        15,
        0,
        8.667,
        -15,
        0,
        9.833,
        15,
        0,
        10.5,
        0
      ]
    },
    {
      "Target": "Parameter",
      "Id": "Param39",
      "FadeInTime": -1.0,
      "FadeOutTime": -1.0,
      "Segments": [
        0,
        0,
        0,
        0.667,
        -15,
        0,
        2.7,
        15,
        0,
        4,
        -15,
        0,
        5.333,
        15,
        0,
        6.333,
        -15,
        0,
        6.833,
        15,
        0,
        7.333,
        -15,
        0,
        8,
        15,
        0,
        9.167,
        -15,
        0,
        10.5,
        0
      ]
    },
    {
      "Target": "Parameter",
      "Id": "Param40",
      "FadeInTime": -1.0,
      "FadeOutTime": -1.0,
      "Segments": [
        0,
        0,
        0,
        1,
        -17,
        0,
        3.033,
        17,
        0,
        4.333,
        -17,
        0,
        5.667,
        17,
        0,
        6.667,
        -17,
        0,
        7.167,
        17,
        0,
        7.667,
        -17,
        0,
        8.333,
        17,
        0,
        9.5,
        -17,
        0,
        10.5,
        0
      ]
    },
    {
      "Target": "Parameter",
      "Id": "Param41",
      "FadeInTime": -1.0,
      "FadeOutTime": -1.0,
      "Segments": [
        0,
        0,
        0,
        1.333,
        -22,
        0,
        3.367,
        22,
        0,
        4.667,
        -22,
        0,
        6,
        22,
        0,
        7,
        -22,
        0,
        7.5,
        22,
        0,
        8,
        -22,
        0,
        8.667,
        22,
        0,
        9.833,
        -22,
        0,
        10.5,
        0
      ]
    },
    {
      "Target": "Parameter",
      "Id": "Param76",
      "FadeInTime": -1.0,
      "FadeOutTime": -1.0,
      "Segments": [
        0,
        0,
        0,
        1.5,
        -17,
        0,
        3.5,
        19,
        0,
        6.333,
        -24,
        1,
        6.444,
        -24,
        6.556,
        -14.185,
        6.667,
        -5,
        1,
        6.778,
        4.185,
        6.889,
        6,
        7,
        6,
        0,
        7.667,
        -6,
        0,
        9.333,
        10,
        0,
        10.5,
        0
      ]
    },
    {
      "Target": "Parameter",
      "Id": "Param77",
      "FadeInTime": -1.0,
      "FadeOutTime": -1.0,
      "Segments": [
        0,
        0,
        0,
        0.333,
        6,
        0,
        1.667,
        -30,
        0,
        4,
        30,
        1,
        4.833,
        30,
        5.667,
        21.994,
        6.5,
        0,
        1,
        6.611,
        -2.933,
        6.722,
        -30,
        6.833,
        -30,
        0,
        7.167,
        8,
        0,
        8.333,
        -30,
        0,
        9.667,
        14,
        0,
        10.5,
        0
      ]
    },
    {
      "Target": "Parameter",
      "Id": "Param78",
      "FadeInTime": -1.0,
      "FadeOutTime": -1.0,
      "Segments": [
        0,
        0,
        0,
        0.5,
        11,
        0,
        1.833,
        -17,
        0,
        4.5,
        17,
        1,
        5.222,
        17,
        5.945,
        12.75,
        6.667,
        0,
        1,
        6.778,
        -1.961,
        6.889,
        -30,
        7,
        -30,
        0,
        7.333,
        10,
        0,
        9,
        -30,
        0,
        10,
        19,
        0,
        10.5,
        0
      ]
    },
    {
      "Target": "Parameter",
      "Id": "Param79",
      "FadeInTime": -1.0,
      "FadeOutTime": -1.0,
      "Segments": [
        0,
        0,
        0,
        1.667,
        -27,
        0,
        3.667,
        19,
        0,
        6.5,
        -18,
        1,
        6.611,
        -18,
        6.722,
        -11.255,
        6.833,
        -4,
        1,
        6.944,
        3.255,
        7.056,
        5,
        7.167,
        5,
        0,
        7.833,
        -6,
        0,
        9.5,
        9,
        0,
        10.5,
        0
      ]
    },
    {
      "Target": "Parameter",
      "Id": "Param80",
      "FadeInTime": -1.0,
      "FadeOutTime": -1.0,
      "Segments": [
        0,
        0,
        0,
        0.5,
        8,
        0,
        1.833,
        -15,
        0,
        4.167,
        15,
        1,
        5,
        15,
        5.834,
        10.995,
        6.667,
        0,
        1,
        6.778,
        -1.466,
        6.889,
        -10,
        7,
        -10,
        0,
        7.333,
        9,
        0,
        8.5,
        -11,
        0,
        9.833,
        14,
        0,
        10.5,
        0
      ]
    },
    {
      "Target": "Parameter",
      "Id": "Param81",
      "FadeInTime": -1.0,
      "FadeOutTime": -1.0,
      "Segments": [
        0,
        0,
        0,
        0.667,
        15,
        0,
        2,
        -19,
        0,
        4.667,
        19,
        1,
        5.389,
        19,
        6.111,
        14.079,
        6.833,
        0,
        1,
        6.944,
        -2.166,
        7.056,
        -15,
        7.167,
        -15,
        0,
        7.5,
        12,
        0,
        9.167,
        -16,
        0,
        10.167,
        21,
        0,
        10.5,
        0
      ]
    },
    {
      "Target": "Parameter",
      "Id": "Param123",
      "FadeInTime": -1.0,
      "FadeOutTime": -1.0,
      "Segments": [
        0,
        0,
        0,
        0.667,
        13,
        0,
        2,
        -15,
        0,
        4,
        13,
        0,
        5.333,
        -15,
        0,
        6.333,
        13,
        0,
        6.667,
        -15,
        0,
        7,
        13,
        0,
        7.333,
        -15,
        0,
        7.833,
        15,
        0,
        8.833,
        -13,
        0,
        9.833,
        15,
        0,
        10.5,
        0
      ]
    },
    {
      "Target": "Parameter",
      "Id": "Param121",
      "FadeInTime": -1.0,
      "FadeOutTime": -1.0,
      "Segments": [
        0,
        0,
        0,
        0.667,
        12,
        0,
        2,
        -14,
        0,
        4,
        12,
        0,
        5.333,
        -14,
        0,
        6.333,
        12,
        0,
        6.667,
        -14,
        0,
        7,
        12,
        0,
        7.333,
        -14,
        0,
        7.833,
        14,
        0,
        8.833,
        -12,
        0,
        9.833,
        14,
        0,
        10.5,
        0
      ]
    },
    {
      "Target": "Parameter",
      "Id": "Param122",
      "FadeInTime": -1.0,
      "FadeOutTime": -1.0,
      "Segments": [
        0,
        0,
        0,
        1.167,
        14,
        0,
        2.5,
        -17,
        0,
        4.5,
        14,
        0,
        5.833,
        -17,
        0,
        6.5,
        14,
        0,
        6.833,
        -17,
        0,
        7.167,
        14,
        0,
        7.6,
        -17,
        0,
        8.333,
        17,
        0,
        9.333,
        -14,
        0,
        10.5,
        0
      ]
    },
    {
      "Target": "Parameter",
      "Id": "Param38",
      "FadeInTime": -1.0,
      "FadeOutTime": -1.0,
      "Segments": [
        0,
        0,
        0,
        0.333,
        -9,
        0,
        1,
        9,
        0,
        1.667,
        -9,
        0,
        2.333,
        6.027,
        0,
        3.333,
        -6.027,
        0,
        4.667,
        7.781,
        0,
        6.333,
        -5,
        0,
        6.833,
        9,
        0,
        7.167,
        -9,
        0,
        7.5,
        9,
        0,
        7.833,
        -9,
        0,
        8.5,
        5,
        0,
        9.167,
        -9,
        0,
        10.5,
        0
      ]
    },
    {
      "Target": "Parameter",
      "Id": "Param82",
      "FadeInTime": -1.0,
      "FadeOutTime": -1.0,
      "Segments": [
        0,
        0,
        0,
        0.5,
        -15,
        0,
        1.167,
        15,
        0,
        1.833,
        -15,
        0,
        2.5,
        10.045,
        0,
        3.5,
        -10.045,
        0,
        4.833,
        12.156,
        0,
        6.5,
        -6,
        0,
        7,
        15,
        0,
        7.333,
        -15,
        0,
        7.667,
        15,
        0,
        8,
        -15,
        0,
        8.667,
        8,
        0,
        9.333,
        -15,
        0,
        10.5,
        0
      ]
    },
    {
      "Target": "Parameter",
      "Id": "Param42",
      "FadeInTime": -1.0,
      "FadeOutTime": -1.0,
      "Segments": [
        0,
        0,
        0,
        0.333,
        -20,
        0,
        1,
        20,
        0,
        1.667,
        -20,
        0,
        2.333,
        13.393,
        0,
        3.333,
        -13.393,
        0,
        4.667,
        15.802,
        0,
        6.333,
        -11,
        0,
        6.833,
        20,
        0,
        7.167,
        -20,
        0,
        7.5,
        20,
        0,
        7.833,
        -20,
        0,
        8.5,
        10,
        0,
        9.167,
        -20,
        0,
        10.5,
        0
      ]
    },
    {
      "Target": "Parameter",
      "Id": "Param83",
      "FadeInTime": -1.0,
      "FadeOutTime": -1.0,
      "Segments": [
        0,
        0,
        0,
        0.5,
        -20,
        0,
        1.167,
        20,
        0,
        1.833,
        -20,
        0,
        2.5,
        13.393,
        0,
        3.5,
        -13.393,
        0,
        4.833,
        15.802,
        0,
        6.5,
        -15,
        0,
        7,
        20,
        0,
        7.333,
        -20,
        0,
        7.667,
        20,
        0,
        8,
        -20,
        0,
        8.667,
        12,
        0,
        9.333,
        -20,
        0,
        10.5,
        0
      ]
    },
    {
      "Target": "Parameter",
      "Id": "Param84",
      "FadeInTime": -1.0,
      "FadeOutTime": -1.0,
      "Segments": [
        0,
        0,
        0,
        10.5,
        0
      ]
    },
    {
      "Target": "Parameter",
      "Id": "Param72",
      "FadeInTime": -1.0,
      "FadeOutTime": -1.0,
      "Segments": [
        0,
        0,
        0,
        10.5,
        0
      ]
    },
    {
      "Target": "Parameter",
      "Id": "Param58",
      "FadeInTime": -1.0,
      "FadeOutTime": -1.0,
      "Segments": [
        0,
        0,
        0,
        0.333,
        10,
        0,
        1,
        -10,
        0,
        1.667,
        10,
        0,
        2.333,
        -6.697,
        0,
        3.333,
        6.697,
        0,
        4.667,
        -6.073,
        0,
        6.333,
        6,
        0,
        6.833,
        -10,
        0,
        7.167,
        10,
        0,
        7.5,
        -10,
        0,
        7.833,
        10,
        0,
        8.5,
        -5,
        0,
        9.167,
        10,
        0,
        10.5,
        0
      ]
    },
    {
      "Target": "Parameter",
      "Id": "Param85",
      "FadeInTime": -1.0,
      "FadeOutTime": -1.0,
      "Segments": [
        0,
        0,
        0,
        0.5,
        13,
        0,
        1.167,
        -13,
        0,
        1.833,
        13,
        0,
        2.5,
        -8.706,
        0,
        3.5,
        8.706,
        0,
        4.833,
        -8.26,
        0,
        6.5,
        6,
        0,
        7,
        -13,
        0,
        7.333,
        13,
        0,
        7.667,
        -13,
        0,
        8,
        13,
        0,
        8.667,
        -7,
        0,
        9.333,
        13,
        0,
        10.5,
        0
      ]
    },
    {
      "Target": "Parameter",
      "Id": "Param59",
      "FadeInTime": -1.0,
      "FadeOutTime": -1.0,
      "Segments": [
        0,
        0,
        0,
        0.333,
        -20,
        0,
        1,
        20,
        0,
        1.667,
        -20,
        0,
        2.333,
        13.393,
        0,
        3.333,
        -13.393,
        0,
        4.667,
        15.802,
        0,
        6.333,
        -11,
        0,
        6.833,
        20,
        0,
        7.167,
        -20,
        0,
        7.5,
        20,
        0,
        7.833,
        -20,
        0,
        8.5,
        10,
        0,
        9.167,
        -20,
        0,
        10.5,
        0
      ]
    },
    {
      "Target": "Parameter",
      "Id": "Param86",
      "FadeInTime": -1.0,
      "FadeOutTime": -1.0,
      "Segments": [
        0,
        0,
        0,
        0.5,
        -22,
        0,
        1.167,
        22,
        0,
        1.833,
        -22,
        0,
        2.5,
        14.732,
        0,
        3.5,
        -14.732,
        0,
        4.833,
        17.26,
        0,
        6.5,
        -13,
        0,
        7,
        22,
        0,
        7.333,
        -22,
        0,
        7.667,
        22,
        0,
        8,
        -22,
        0,
        8.667,
        12,
        0,
        9.333,
        -22,
        0,
        10.5,
        0
      ]
    },
    {
      "Target": "Parameter",
      "Id": "Param73",
      "FadeInTime": -1.0,
      "FadeOutTime": -1.0,
      "Segments": [
        0,
        0,
        0,
        10.5,
        0
      ]
    },
    {
      "Target": "Parameter",
      "Id": "Param124",
      "FadeInTime": -1.0,
      "FadeOutTime": -1.0,
      "Segments": [
        0,
        0,
        0,
        1.717,
        -16,
        0,
        3.45,
        0,
        0,
        5.167,
        -16,
        0,
        6.967,
        0,
        0,
        8.683,
        -16,
        0,
        10.5,
        0
      ]
    },
    {
      "Target": "Parameter",
      "Id": "Param125",
      "FadeInTime": -1.0,
      "FadeOutTime": -1.0,
      "Segments": [
        0,
        0,
        0,
        1.15,
        17,
        0,
        3.45,
        0,
        0,
        4.6,
        17,
        0,
        6.967,
        0,
        0,
        8.117,
        17,
        0,
        10.5,
        0
      ]
    },
    {
      "Target": "Parameter",
      "Id": "Param126",
      "FadeInTime": -1.0,
      "FadeOutTime": -1.0,
      "Segments": [
        0,
        0,
        0,
        2.483,
        -10,
        0,
        3.45,
        0,
        0,
        5.933,
        -10,
        0,
        6.967,
        0,
        0,
        9.45,
        -10,
        0,
        10.5,
        0
      ]
    },
    {
      "Target": "Parameter",
      "Id": "Param127",
      "FadeInTime": -1.0,
      "FadeOutTime": -1.0,
      "Segments": [
        0,
        0,
        0,
        1.917,
        -17,
        0,
        3.45,
        0,
        0,
        5.367,
        -17,
        0,
        6.967,
        0,
        0,
        8.883,
        -17,
        0,
        10.5,
        0
      ]
    },
    {
      "Target": "Parameter",
      "Id": "Param128",
      "FadeInTime": -1.0,
      "FadeOutTime": -1.0,
      "Segments": [
        0,
        0,
        0,
        1.333,
        8,
        0,
        3.45,
        0,
        0,
        4.783,
        8,
        0,
        6.967,
        0,
        0,
        8.3,
        8,
        0,
        10.5,
        0
      ]
    },
    {
      "Target": "Parameter",
      "Id": "Param129",
      "FadeInTime": -1.0,
      "FadeOutTime": -1.0,
      "Segments": [
        0,
        0,
        0,
        1.717,
        -4.885,
        0,
        3.45,
        0,
        0,
        5.167,
        -4.885,
        0,
        6.967,
        0,
        0,
        8.683,
        -4.885,
        0,
        10.5,
        0
      ]
    },
    {
      "Target": "Parameter",
      "Id": "Param130",
      "FadeInTime": -1.0,
      "FadeOutTime": -1.0,
      "Segments": [
        0,
        0,
        0,
        0.767,
        -6.979,
        0,
        2.683,
        6.979,
        0,
        3.45,
        0,
        1,
        3.706,
        -4.653,
        3.961,
        -6.979,
        4.217,
        -6.979,
        0,
        6.133,
        6.979,
        0,
        6.967,
        0,
        1,
        7.222,
        -4.451,
        7.478,
        -6.979,
        7.733,
        -6.979,
        0,
        9.65,
        6.979,
        0,
        10.5,
        0
      ]
    },
    {
      "Target": "Parameter",
      "Id": "Param131",
      "FadeInTime": -1.0,
      "FadeOutTime": -1.0,
      "Segments": [
        0,
        0,
        0,
        0.767,
        -3.489,
        0,
        2.683,
        3.489,
        0,
        3.45,
        0,
        1,
        3.706,
        -2.326,
        3.961,
        -3.489,
        4.217,
        -3.489,
        0,
        6.133,
        3.489,
        0,
        6.967,
        0,
        1,
        7.222,
        -2.225,
        7.478,
        -3.489,
        7.733,
        -3.489,
        0,
        9.65,
        3.489,
        0,
        10.5,
        0
      ]
    },
    {
      "Target": "Parameter",
      "Id": "Param132",
      "FadeInTime": -1.0,
      "FadeOutTime": -1.0,
      "Segments": [
        0,
        0,
        0,
        1.717,
        12,
        0,
        3.45,
        0,
        0,
        5.167,
        12,
        0,
        6.967,
        0,
        0,
        8.683,
        12,
        0,
        10.5,
        0
      ]
    },
    {
      "Target": "Parameter",
      "Id": "Param133",
      "FadeInTime": -1.0,
      "FadeOutTime": -1.0,
      "Segments": [
        0,
        0,
        0,
        1.717,
        4.885,
        0,
        3.45,
        0,
        0,
        5.167,
        4.885,
        0,
        6.967,
        0,
        0,
        8.683,
        4.885,
        0,
        10.5,
        0
      ]
    },
    {
      "Target": "Parameter",
      "Id": "Param134",
      "FadeInTime": -1.0,
      "FadeOutTime": -1.0,
      "Segments": [
        0,
        0,
        0,
        0.767,
        2.094,
        0,
        2.683,
        -2.094,
        0,
        3.45,
        0,
        1,
        3.706,
        1.396,
        3.961,
        2.094,
        4.217,
        2.094,
        0,
        6.133,
        -2.094,
        0,
        6.967,
        0,
        1,
        7.222,
        1.336,
        7.478,
        2.094,
        7.733,
        2.094,
        0,
        9.65,
        -2.094,
        0,
        10.5,
        0
      ]
    },
    {
      "Target": "Parameter",
      "Id": "Param135",
      "FadeInTime": -1.0,
      "FadeOutTime": -1.0,
      "Segments": [
        0,
        0,
        0,
        1.717,
        -2.791,
        0,
        3.45,
        0,
        0,
        5.167,
        -2.791,
        0,
        6.967,
        0,
        0,
        8.683,
        -2.791,
        0,
        10.5,
        0
      ]
    },
    {
      "Target": "Parameter",
      "Id": "Param136",
      "FadeInTime": -1.0,
      "FadeOutTime": -1.0,
      "Segments": [
        0,
        0,
        0,
        1.717,
        -3.489,
        0,
        3.45,
        0,
        0,
        5.167,
        -3.489,
        0,
        6.967,
        0,
        0,
        8.683,
        -3.489,
        0,
        10.5,
        0
      ]
    },
    {
      "Target": "Parameter",
      "Id": "Param138",
      "FadeInTime": -1.0,
      "FadeOutTime": -1.0,
      "Segments": [
        0,
        0,
        0,
        0.767,
        15,
        0,
        2.683,
        -15,
        0,
        3.45,
        0,
        1,
        3.706,
        10,
        3.961,
        15,
        4.217,
        15,
        0,
        6.133,
        -15,
        0,
        6.967,
        0,
        1,
        7.222,
        9.565,
        7.478,
        15,
        7.733,
        15,
        0,
        9.65,
        -15,
        0,
        10.5,
        0
      ]
    },
    {
      "Target": "Parameter",
      "Id": "Param139",
      "FadeInTime": -1.0,
      "FadeOutTime": -1.0,
      "Segments": [
        0,
        0,
        0,
        1.717,
        20,
        0,
        3.45,
        0,
        0,
        5.167,
        20,
        0,
        6.967,
        0,
        0,
        8.683,
        20,
        0,
        10.5,
        0
      ]
    },
    {
      "Target": "Parameter",
      "Id": "Param140",
      "FadeInTime": -1.0,
      "FadeOutTime": -1.0,
      "Segments": [
        0,
        0,
        0,
        0.767,
        4,
        0,
        2.683,
        -4,
        0,
        3.45,
        0,
        1,
        3.706,
        2.667,
        3.961,
        4,
        4.217,
        4,
        0,
        6.133,
        -4,
        0,
        6.967,
        0,
        1,
        7.222,
        2.551,
        7.478,
        4,
        7.733,
        4,
        0,
        9.65,
        -4,
        0,
        10.5,
        0
      ]
    },
    {
      "Target": "Parameter",
      "Id": "Param141",
      "FadeInTime": -1.0,
      "FadeOutTime": -1.0,
      "Segments": [
        0,
        0,
        0,
        1.717,
        -30,
        0,
        3.45,
        0,
        0,
        5.167,
        -30,
        0,
        6.967,
        0,
        0,
        8.683,
        -30,
        0,
        10.5,
        0
      ]
    },
    {
      "Target": "Parameter",
      "Id": "Param142",
      "FadeInTime": -1.0,
      "FadeOutTime": -1.0,
      "Segments": [
        0,
        0,
        0,
        0.767,
        -4,
        0,
        2.683,
        4,
        0,
        3.45,
        0,
        1,
        3.706,
        -2.667,
        3.961,
        -4,
        4.217,
        -4,
        0,
        6.133,
        4,
        0,
        6.967,
        0,
        1,
        7.222,
        -2.551,
        7.478,
        -4,
        7.733,
        -4,
        0,
        9.65,
        4,
        0,
        10.5,
        0
      ]
    },
    {
      "Target": "Parameter",
      "Id": "Param143",
      "FadeInTime": -1.0,
      "FadeOutTime": -1.0,
      "Segments": [
        0,
        0,
        0,
        1.717,
        -12,
        0,
        3.45,
        0,
        0,
        5.167,
        -12,
        0,
        6.967,
        0,
        0,
        8.683,
        -12,
        0,
        10.5,
        0
      ]
    },
    {
      "Target": "Parameter",
      "Id": "Param144",
      "FadeInTime": -1.0,
      "FadeOutTime": -1.0,
      "Segments": [
        0,
        0,
        0,
        1.717,
        5,
        0,
        3.45,
        0,
        0,
        5.167,
        5,
        0,
        6.967,
        0,
        0,
        8.683,
        5,
        0,
        10.5,
        0
      ]
    },
    {
      "Target": "Parameter",
      "Id": "Param145",
      "FadeInTime": -1.0,
      "FadeOutTime": -1.0,
      "Segments": [
        0,
        0,
        0,
        1.15,
        -10,
        0,
        3.45,
        0,
        0,
        4.6,
        -10,
        0,
        6.967,
        0,
        0,
        8.117,
        -10,
        0,
        10.5,
        0
      ]
    },
    {
      "Target": "Parameter",
      "Id": "Param146",
      "FadeInTime": -1.0,
      "FadeOutTime": -1.0,
      "Segments": [
        0,
        0,
        0,
        2.3,
        -30,
        0,
        3.45,
        0,
        0,
        5.75,
        -30,
        0,
        6.967,
        0,
        0,
        9.267,
        -30,
        0,
        10.5,
        0
      ]
    },
    {
      "Target": "Parameter",
      "Id": "Param147",
      "FadeInTime": -1.0,
      "FadeOutTime": -1.0,
      "Segments": [
        0,
        0,
        0,
        1.717,
        -5,
        0,
        3.45,
        0,
        0,
        5.167,
        -5,
        0,
        6.967,
        0,
        0,
        8.683,
        -5,
        0,
        10.5,
        0
      ]
    },
    {
      "Target": "Parameter",
      "Id": "Param148",
      "FadeInTime": -1.0,
      "FadeOutTime": -1.0,
      "Segments": [
        0,
        0,
        0,
        1.717,
        -18,
        0,
        3.45,
        0,
        0,
        5.167,
        -18,
        0,
        6.967,
        0,
        0,
        8.683,
        -18,
        0,
        10.5,
        0
      ]
    },
    {
      "Target": "Parameter",
      "Id": "Param149",
      "FadeInTime": -1.0,
      "FadeOutTime": -1.0,
      "Segments": [
        0,
        0,
        0,
        1.717,
        6,
        0,
        3.45,
        0,
        0,
        5.167,
        6,
        0,
        6.967,
        0,
        0,
        8.683,
        6,
        0,
        10.5,
        0
      ]
    },
    {
      "Target": "Parameter",
      "Id": "Param150",
      "FadeInTime": -1.0,
      "FadeOutTime": -1.0,
      "Segments": [
        0,
        0,
        0,
        0.767,
        -3,
        0,
        2.683,
        3,
        0,
        3.45,
        0,
        1,
        3.706,
        -2,
        3.961,
        -3,
        4.217,
        -3,
        0,
        6.133,
        3,
        0,
        6.967,
        0,
        1,
        7.222,
        -1.913,
        7.478,
        -3,
        7.733,
        -3,
        0,
        9.65,
        3,
        0,
        10.5,
        0
      ]
    },
    {
      "Target": "Parameter",
      "Id": "Param151",
      "FadeInTime": -1.0,
      "FadeOutTime": -1.0,
      "Segments": [
        0,
        0,
        0,
        1.717,
        11,
        0,
        3.45,
        0,
        0,
        5.167,
        11,
        0,
        6.967,
        0,
        0,
        8.683,
        11,
        0,
        10.5,
        0
      ]
    },
    {
      "Target": "Parameter",
      "Id": "Param152",
      "FadeInTime": -1.0,
      "FadeOutTime": -1.0,
      "Segments": [
        0,
        0,
        0,
        1.717,
        30,
        0,
        3.45,
        0,
        0,
        5.167,
        30,
        0,
        6.967,
        0,
        0,
        8.683,
        30,
        0,
        10.5,
        0
      ]
    },
    {
      "Target": "Parameter",
      "Id": "Param153",
      "FadeInTime": -1.0,
      "FadeOutTime": -1.0,
      "Segments": [
        0,
        0,
        0,
        1.717,
        2,
        0,
        3.45,
        0,
        0,
        5.167,
        2,
        0,
        6.967,
        0,
        0,
        8.683,
        2,
        0,
        10.5,
        0
      ]
    },
    {
      "Target": "Parameter",
      "Id": "Param154",
      "FadeInTime": -1.0,
      "FadeOutTime": -1.0,
      "Segments": [
        0,
        0,
        0,
        1.717,
        -4,
        0,
        3.45,
        0,
        0,
        5.167,
        -4,
        0,
        6.967,
        0,
        0,
        8.683,
        -4,
        0,
        10.5,
        0
      ]
    },
    {
      "Target": "Parameter",
      "Id": "Param155",
      "FadeInTime": -1.0,
      "FadeOutTime": -1.0,
      "Segments": [
        0,
        0,
        0,
        0.767,
        3,
        0,
        2.683,
        -3,
        0,
        3.45,
        0,
        1,
        3.706,
        2,
        3.961,
        3,
        4.217,
        3,
        0,
        6.133,
        -3,
        0,
        6.967,
        0,
        1,
        7.222,
        1.913,
        7.478,
        3,
        7.733,
        3,
        0,
        9.65,
        -3,
        0,
        10.5,
        0
      ]
    }
  ],
  "UserData": []
}