{
  "Version": 3,
  "Name": "huiyeji04_qianjing",
  "FileReferences": {
    "Moc": "huiyeji04_qianjing.moc3",
    "Textures": [
      "textures/texture_00.png"
    ],
    "Physics": null,
    "Pose": null,
    "DisplayInfo": "huiyeji04_qianjing.cdi3.json",
    "Motions": {
      "idle01": [
        {
          "File": "motions/idle01.motion3.json"
        }
      ]
    },
    "Expressions": []
  },
  "Groups": [
    {
      "Target": "Parameter",
      "Name": "EyeBlink",
      "Ids": [
        "ParamEyeLOpen",
        "ParamEyeROpen"
      ]
    },
    {
      "Target": "Parameter",
      "Name": "LipSync",
      "Ids": [
        "ParamMouthOpenY"
      ]
    }
  ]
}